[{"ScoreId": 15823, "Season": 2015, "SeasonType": 1, "Week": 16, "Day": "2015-12-24T00:00:00", "DateTime": "2015-12-24T20:25:00", "Status": "F/OT", "AwayTeamId": 29, "HomeTeamId": 25, "AwayTeamName": "LAC", "HomeTeamName": "LV", "GlobalGameId": 15823, "GlobalAwayTeamId": 29, "GlobalHomeTeamId": 25, "HomeTeamScore": 15, "AwayTeamScore": 13, "TotalScore": 27, "HomeRotationNumber": null, "AwayRotationNumber": null, "PregameOdds": [], "LiveOdds": [], "AlternateMarketPregameOdds": []}, {"ScoreId": 15824, "Season": 2015, "SeasonType": 1, "Week": 16, "Day": "2015-12-26T00:00:00", "DateTime": "2015-12-26T20:25:00", "Status": "Final", "AwayTeamId": 35, "HomeTeamId": 26, "AwayTeamName": "WAS", "HomeTeamName": "PHI", "GlobalGameId": 15824, "GlobalAwayTeamId": 35, "GlobalHomeTeamId": 26, "HomeTeamScore": 15, "AwayTeamScore": 24, "TotalScore": 39, "HomeRotationNumber": null, "AwayRotationNumber": null, "PregameOdds": [], "LiveOdds": [], "AlternateMarketPregameOdds": []}, {"ScoreId": 15825, "Season": 2015, "SeasonType": 1, "Week": 16, "Day": "2015-12-27T00:00:00", "DateTime": "2015-12-27T13:00:00", "Status": "F/OT", "AwayTeamId": 21, "HomeTeamId": 24, "AwayTeamName": "NE", "HomeTeamName": "NYJ", "GlobalGameId": 15825, "GlobalAwayTeamId": 21, "GlobalHomeTeamId": 24, "HomeTeamScore": 17, "AwayTeamScore": 13, "TotalScore": 29, "HomeRotationNumber": null, "AwayRotationNumber": null, "PregameOdds": [], "LiveOdds": [], "AlternateMarketPregameOdds": []}, {"ScoreId": 15826, "Season": 2015, "SeasonType": 1, "Week": 16, "Day": "2015-12-27T00:00:00", "DateTime": "2015-12-27T13:00:00", "Status": "Final", "AwayTeamId": 13, "HomeTeamId": 34, "AwayTeamName": "HOU", "HomeTeamName": "TEN", "GlobalGameId": 15826, "GlobalAwayTeamId": 13, "GlobalHomeTeamId": 34, "HomeTeamScore": 2, "AwayTeamScore": 22, "TotalScore": 25, "HomeRotationNumber": null, "AwayRotationNumber": null, "PregameOdds": [], "LiveOdds": [], "AlternateMarketPregameOdds": []}, {"ScoreId": 15827, "Season": 2015, "SeasonType": 1, "Week": 16, "Day": "2015-12-27T00:00:00", "DateTime": "2015-12-27T13:00:00", "Status": "Final", "AwayTeamId": 8, "HomeTeamId": 16, "AwayTeamName": "CLE", "HomeTeamName": "KC", "GlobalGameId": 15827, "GlobalAwayTeamId": 8, "GlobalHomeTeamId": 16, "HomeTeamScore": 11, "AwayTeamScore": 5, "TotalScore": 19, "HomeRotationNumber": null, "AwayRotationNumber": null, "PregameOdds": [], "LiveOdds": [], "AlternateMarketPregameOdds": []}, {"ScoreId": 15828, "Season": 2015, "SeasonType": 1, "Week": 16, "Day": "2015-12-27T00:00:00", "DateTime": "2015-12-27T13:00:00", "Status": "Final", "AwayTeamId": 14, "HomeTeamId": 19, "AwayTeamName": "IND", "HomeTeamName": "MIA", "GlobalGameId": 15828, "GlobalAwayTeamId": 14, "GlobalHomeTeamId": 19, "HomeTeamScore": 5, "AwayTeamScore": 11, "TotalScore": 19, "HomeRotationNumber": null, "AwayRotationNumber": null, "PregameOdds": [], "LiveOdds": [], "AlternateMarketPregameOdds": []}, {"ScoreId": 15830, "Season": 2015, "SeasonType": 1, "Week": 16, "Day": "2015-12-27T00:00:00", "DateTime": "2015-12-27T13:00:00", "Status": "Final", "AwayTeamId": 31, "HomeTeamId": 11, "AwayTeamName": "SF", "HomeTeamName": "DET", "GlobalGameId": 15830, "GlobalAwayTeamId": 31, "GlobalHomeTeamId": 11, "HomeTeamScore": 20, "AwayTeamScore": 11, "TotalScore": 31, "HomeRotationNumber": null, "AwayRotationNumber": null, "PregameOdds": [], "LiveOdds": [], "AlternateMarketPregameOdds": []}, {"ScoreId": 15831, "Season": 2015, "SeasonType": 1, "Week": 16, "Day": "2015-12-27T00:00:00", "DateTime": "2015-12-27T13:00:00", "Status": "Final", "AwayTeamId": 9, "HomeTeamId": 4, "AwayTeamName": "DAL", "HomeTeamName": "BUF", "GlobalGameId": 15831, "GlobalAwayTeamId": 9, "GlobalHomeTeamId": 4, "HomeTeamScore": 10, "AwayTeamScore": 2, "TotalScore": 14, "HomeRotationNumber": null, "AwayRotationNumber": null, "PregameOdds": [], "LiveOdds": [], "AlternateMarketPregameOdds": []}, {"ScoreId": 15832, "Season": 2015, "SeasonType": 1, "Week": 16, "Day": "2015-12-27T00:00:00", "DateTime": "2015-12-27T13:00:00", "Status": "Final", "AwayTeamId": 6, "HomeTeamId": 33, "AwayTeamName": "CHI", "HomeTeamName": "TB", "GlobalGameId": 15832, "GlobalAwayTeamId": 6, "GlobalHomeTeamId": 33, "HomeTeamScore": 13, "AwayTeamScore": 17, "TotalScore": 30, "HomeRotationNumber": null, "AwayRotationNumber": null, "PregameOdds": [], "LiveOdds": [], "AlternateMarketPregameOdds": []}, {"ScoreId": 15833, "Season": 2015, "SeasonType": 1, "Week": 16, "Day": "2015-12-27T00:00:00", "DateTime": "2015-12-27T13:00:00", "Status": "Final", "AwayTeamId": 5, "HomeTeamId": 2, "AwayTeamName": "CAR", "HomeTeamName": "ATL", "GlobalGameId": 15833, "GlobalAwayTeamId": 5, "GlobalHomeTeamId": 2, "HomeTeamScore": 13, "AwayTeamScore": 5, "TotalScore": 21, "HomeRotationNumber": null, "AwayRotationNumber": null, "PregameOdds": [], "LiveOdds": [], "AlternateMarketPregameOdds": []}, {"ScoreId": 15837, "Season": 2015, "SeasonType": 1, "Week": 16, "Day": "2015-12-27T00:00:00", "DateTime": "2015-12-27T13:00:00", "Status": "Final", "AwayTeamId": 28, "HomeTeamId": 3, "AwayTeamName": "PIT", "HomeTeamName": "BAL", "GlobalGameId": 15837, "GlobalAwayTeamId": 28, "GlobalHomeTeamId": 3, "HomeTeamScore": 13, "AwayTeamScore": 11, "TotalScore": 24, "HomeRotationNumber": null, "AwayRotationNumber": null, "PregameOdds": [], "LiveOdds": [], "AlternateMarketPregameOdds": []}, {"ScoreId": 15829, "Season": 2015, "SeasonType": 1, "Week": 16, "Day": "2015-12-27T00:00:00", "DateTime": "2015-12-27T16:05:00", "Status": "Final", "AwayTeamId": 15, "HomeTeamId": 22, "AwayTeamName": "JAX", "HomeTeamName": "NO", "GlobalGameId": 15829, "GlobalAwayTeamId": 15, "GlobalHomeTeamId": 22, "HomeTeamScore": 24, "AwayTeamScore": 17, "TotalScore": 41, "HomeRotationNumber": null, "AwayRotationNumber": null, "PregameOdds": [], "LiveOdds": [], "AlternateMarketPregameOdds": []}, {"ScoreId": 15835, "Season": 2015, "SeasonType": 1, "Week": 16, "Day": "2015-12-27T00:00:00", "DateTime": "2015-12-27T16:25:00", "Status": "Final", "AwayTeamId": 32, "HomeTeamId": 30, "AwayTeamName": "LAR", "HomeTeamName": "SEA", "GlobalGameId": 15835, "GlobalAwayTeamId": 32, "GlobalHomeTeamId": 30, "HomeTeamScore": 11, "AwayTeamScore": 15, "TotalScore": 25, "HomeRotationNumber": null, "AwayRotationNumber": null, "PregameOdds": [], "LiveOdds": [], "AlternateMarketPregameOdds": []}, {"ScoreId": 15836, "Season": 2015, "SeasonType": 1, "Week": 16, "Day": "2015-12-27T00:00:00", "DateTime": "2015-12-27T16:25:00", "Status": "Final", "AwayTeamId": 12, "HomeTeamId": 1, "AwayTeamName": "GB", "HomeTeamName": "ARI", "GlobalGameId": 15836, "GlobalAwayTeamId": 12, "GlobalHomeTeamId": 1, "HomeTeamScore": 24, "AwayTeamScore": 3, "TotalScore": 29, "HomeRotationNumber": null, "AwayRotationNumber": null, "PregameOdds": [], "LiveOdds": [], "AlternateMarketPregameOdds": []}, {"ScoreId": 15834, "Season": 2015, "SeasonType": 1, "Week": 16, "Day": "2015-12-27T00:00:00", "DateTime": "2015-12-27T20:30:00", "Status": "Final", "AwayTeamId": 23, "HomeTeamId": 20, "AwayTeamName": "NYG", "HomeTeamName": "MIN", "GlobalGameId": 15834, "GlobalAwayTeamId": 23, "GlobalHomeTeamId": 20, "HomeTeamScore": 31, "AwayTeamScore": 11, "TotalScore": 42, "HomeRotationNumber": null, "AwayRotationNumber": null, "PregameOdds": [], "LiveOdds": [], "AlternateMarketPregameOdds": []}, {"ScoreId": 15838, "Season": 2015, "SeasonType": 1, "Week": 16, "Day": "2015-12-28T00:00:00", "DateTime": "2015-12-28T20:30:00", "Status": "F/OT", "AwayTeamId": 7, "HomeTeamId": 10, "AwayTeamName": "CIN", "HomeTeamName": "DEN", "GlobalGameId": 15838, "GlobalAwayTeamId": 7, "GlobalHomeTeamId": 10, "HomeTeamScore": 13, "AwayTeamScore": 11, "TotalScore": 24, "HomeRotationNumber": null, "AwayRotationNumber": null, "PregameOdds": [], "LiveOdds": [], "AlternateMarketPregameOdds": []}]