[{"ScoreId": 17343, "Season": 2020, "SeasonType": 1, "Week": 6, "Day": "2020-10-18T00:00:00", "DateTime": "2020-10-18T13:00:00", "Status": "F/OT", "AwayTeamId": 13, "HomeTeamId": 34, "AwayTeamName": "HOU", "HomeTeamName": "TEN", "GlobalGameId": 17343, "GlobalAwayTeamId": 13, "GlobalHomeTeamId": 34, "HomeTeamScore": 29, "AwayTeamScore": 25, "TotalScore": 53, "HomeRotationNumber": 176, "AwayRotationNumber": 175, "PregameOdds": [{"GameOddId": 639481, "Sportsbook": "Scrambled", "ScoreId": 17343, "Created": "2020-10-18T12:52:00", "Updated": "2020-10-18T12:59:49", "HomeMoneyLine": -136, "AwayMoneyLine": 119, "DrawMoneyLine": null, "HomePointSpread": -2.7, "AwayPointSpread": 1.9, "HomePointSpreadPayout": -75, "AwayPointSpreadPayout": -75, "OverUnder": 35.4, "OverPayout": -75, "UnderPayout": -75, "SportsbookId": 7, "OddType": "pregame", "SportsbookUrl": null}, {"GameOddId": 639519, "Sportsbook": "Scrambled", "ScoreId": 17343, "Created": "2020-10-18T12:56:28", "Updated": "2020-10-18T12:59:50", "HomeMoneyLine": -140, "AwayMoneyLine": 117, "DrawMoneyLine": null, "HomePointSpread": -2.7, "AwayPointSpread": 1.9, "HomePointSpreadPayout": -72, "AwayPointSpreadPayout": -78, "OverUnder": 35.4, "OverPayout": -72, "UnderPayout": -78, "SportsbookId": 8, "OddType": "pregame", "SportsbookUrl": null}, {"GameOddId": 639468, "Sportsbook": "Scrambled", "ScoreId": 17343, "Created": "2020-10-18T12:51:26", "Updated": "2020-10-18T12:59:51", "HomeMoneyLine": -136, "AwayMoneyLine": 119, "DrawMoneyLine": null, "HomePointSpread": -2.7, "AwayPointSpread": 1.9, "HomePointSpreadPayout": -73, "AwayPointSpreadPayout": -73, "OverUnder": 35.4, "OverPayout": -73, "UnderPayout": -73, "SportsbookId": 9, "OddType": "pregame", "SportsbookUrl": null}, {"GameOddId": 639467, "Sportsbook": "Scrambled", "ScoreId": 17343, "Created": "2020-10-18T12:51:25", "Updated": "2020-10-18T12:59:50", "HomeMoneyLine": -136, "AwayMoneyLine": 119, "DrawMoneyLine": null, "HomePointSpread": -2.7, "AwayPointSpread": 1.9, "HomePointSpreadPayout": -73, "AwayPointSpreadPayout": -73, "OverUnder": 35.4, "OverPayout": -73, "UnderPayout": -73, "SportsbookId": 10, "OddType": "pregame", "SportsbookUrl": null}, {"GameOddId": 639471, "Sportsbook": "Scrambled", "ScoreId": 17343, "Created": "2020-10-18T12:51:27", "Updated": "2020-10-18T12:59:52", "HomeMoneyLine": -143, "AwayMoneyLine": 116, "DrawMoneyLine": null, "HomePointSpread": -2.7, "AwayPointSpread": 1.9, "HomePointSpreadPayout": -75, "AwayPointSpreadPayout": -75, "OverUnder": 35.4, "OverPayout": -75, "UnderPayout": -75, "SportsbookId": 12, "OddType": "pregame", "SportsbookUrl": null}, {"GameOddId": 639470, "Sportsbook": "Scrambled", "ScoreId": 17343, "Created": "2020-10-18T12:51:26", "Updated": "2020-10-18T12:59:52", "HomeMoneyLine": -143, "AwayMoneyLine": 116, "DrawMoneyLine": null, "HomePointSpread": -2.7, "AwayPointSpread": 1.9, "HomePointSpreadPayout": -75, "AwayPointSpreadPayout": -75, "OverUnder": 35.4, "OverPayout": -75, "UnderPayout": -75, "SportsbookId": 13, "OddType": "pregame", "SportsbookUrl": null}, {"GameOddId": 639472, "Sportsbook": "Scrambled", "ScoreId": 17343, "Created": "2020-10-18T12:51:27", "Updated": "2020-10-18T12:59:53", "HomeMoneyLine": -136, "AwayMoneyLine": 119, "DrawMoneyLine": null, "HomePointSpread": -2.7, "AwayPointSpread": 1.9, "HomePointSpreadPayout": -73, "AwayPointSpreadPayout": -73, "OverUnder": 35.4, "OverPayout": -73, "UnderPayout": -73, "SportsbookId": 14, "OddType": "pregame", "SportsbookUrl": null}, {"GameOddId": 639521, "Sportsbook": "Scrambled", "ScoreId": 17343, "Created": "2020-10-18T12:56:34", "Updated": "2020-10-18T12:59:56", "HomeMoneyLine": -138, "AwayMoneyLine": 117, "DrawMoneyLine": null, "HomePointSpread": -2.7, "AwayPointSpread": 1.9, "HomePointSpreadPayout": -74, "AwayPointSpreadPayout": -74, "OverUnder": 35.4, "OverPayout": -74, "UnderPayout": -75, "SportsbookId": 22, "OddType": "pregame", "SportsbookUrl": null}, {"GameOddId": 639511, "Sportsbook": "Scrambled", "ScoreId": 17343, "Created": "2020-10-18T12:54:38", "Updated": "2020-10-18T12:59:54", "HomeMoneyLine": -133, "AwayMoneyLine": 112, "DrawMoneyLine": null, "HomePointSpread": -2.4, "AwayPointSpread": 1.6, "HomePointSpreadPayout": -75, "AwayPointSpreadPayout": -75, "OverUnder": 35.4, "OverPayout": -72, "UnderPayout": -78, "SportsbookId": 23, "OddType": "pregame", "SportsbookUrl": null}, {"GameOddId": 639473, "Sportsbook": "Scrambled", "ScoreId": 17343, "Created": "2020-10-18T12:51:28", "Updated": "2020-10-18T12:59:55", "HomeMoneyLine": -143, "AwayMoneyLine": 116, "DrawMoneyLine": null, "HomePointSpread": -2.7, "AwayPointSpread": 1.9, "HomePointSpreadPayout": -75, "AwayPointSpreadPayout": -75, "OverUnder": 35.4, "OverPayout": -75, "UnderPayout": -75, "SportsbookId": 25, "OddType": "pregame", "SportsbookUrl": null}], "LiveOdds": [], "AlternateMarketPregameOdds": []}, {"ScoreId": 17344, "Season": 2020, "SeasonType": 1, "Week": 6, "Day": "2020-10-18T00:00:00", "DateTime": "2020-10-18T13:00:00", "Status": "Final", "AwayTeamId": 7, "HomeTeamId": 14, "AwayTeamName": "CIN", "HomeTeamName": "IND", "GlobalGameId": 17344, "GlobalAwayTeamId": 7, "GlobalHomeTeamId": 14, "HomeTeamScore": 21, "AwayTeamScore": 18, "TotalScore": 39, "HomeRotationNumber": 181, "AwayRotationNumber": 180, "PregameOdds": [{"GameOddId": 639162, "Sportsbook": "Scrambled", "ScoreId": 17344, "Created": "2020-10-18T11:33:07", "Updated": "2020-10-18T12:59:49", "HomeMoneyLine": -255, "AwayMoneyLine": 211, "DrawMoneyLine": null, "HomePointSpread": -5.1, "AwayPointSpread": 3.5, "HomePointSpreadPayout": -73, "AwayPointSpreadPayout": -78, "OverUnder": 31.3, "OverPayout": -75, "UnderPayout": -74, "SportsbookId": 7, "OddType": "pregame", "SportsbookUrl": null}, {"GameOddId": 638868, "Sportsbook": "Scrambled", "ScoreId": 17344, "Created": "2020-10-18T10:50:35", "Updated": "2020-10-18T12:59:50", "HomeMoneyLine": -228, "AwayMoneyLine": 184, "DrawMoneyLine": null, "HomePointSpread": -5.1, "AwayPointSpread": 3.5, "HomePointSpreadPayout": -72, "AwayPointSpreadPayout": -78, "OverUnder": 31.3, "OverPayout": -75, "UnderPayout": -75, "SportsbookId": 8, "OddType": "pregame", "SportsbookUrl": null}, {"GameOddId": 639156, "Sportsbook": "Scrambled", "ScoreId": 17344, "Created": "2020-10-18T11:32:49", "Updated": "2020-10-18T12:59:51", "HomeMoneyLine": -255, "AwayMoneyLine": 211, "DrawMoneyLine": null, "HomePointSpread": -5.1, "AwayPointSpread": 3.5, "HomePointSpreadPayout": -71, "AwayPointSpreadPayout": -75, "OverUnder": 31.3, "OverPayout": -74, "UnderPayout": -72, "SportsbookId": 9, "OddType": "pregame", "SportsbookUrl": null}, {"GameOddId": 639155, "Sportsbook": "Scrambled", "ScoreId": 17344, "Created": "2020-10-18T11:32:48", "Updated": "2020-10-18T12:59:50", "HomeMoneyLine": -255, "AwayMoneyLine": 211, "DrawMoneyLine": null, "HomePointSpread": -5.1, "AwayPointSpread": 3.5, "HomePointSpreadPayout": -71, "AwayPointSpreadPayout": -75, "OverUnder": 31.3, "OverPayout": -74, "UnderPayout": -72, "SportsbookId": 10, "OddType": "pregame", "SportsbookUrl": null}, {"GameOddId": 639158, "Sportsbook": "Scrambled", "ScoreId": 17344, "Created": "2020-10-18T11:32:51", "Updated": "2020-10-18T12:59:52", "HomeMoneyLine": -262, "AwayMoneyLine": 201, "DrawMoneyLine": null, "HomePointSpread": -5.1, "AwayPointSpread": 3.5, "HomePointSpreadPayout": -73, "AwayPointSpreadPayout": -78, "OverUnder": 31.3, "OverPayout": -75, "UnderPayout": -74, "SportsbookId": 12, "OddType": "pregame", "SportsbookUrl": null}, {"GameOddId": 639157, "Sportsbook": "Scrambled", "ScoreId": 17344, "Created": "2020-10-18T11:32:50", "Updated": "2020-10-18T12:59:52", "HomeMoneyLine": -262, "AwayMoneyLine": 201, "DrawMoneyLine": null, "HomePointSpread": -5.1, "AwayPointSpread": 3.5, "HomePointSpreadPayout": -73, "AwayPointSpreadPayout": -78, "OverUnder": 31.3, "OverPayout": -75, "UnderPayout": -74, "SportsbookId": 13, "OddType": "pregame", "SportsbookUrl": null}, {"GameOddId": 639159, "Sportsbook": "Scrambled", "ScoreId": 17344, "Created": "2020-10-18T11:32:51", "Updated": "2020-10-18T12:59:53", "HomeMoneyLine": -255, "AwayMoneyLine": 211, "DrawMoneyLine": null, "HomePointSpread": -5.1, "AwayPointSpread": 3.5, "HomePointSpreadPayout": -71, "AwayPointSpreadPayout": -75, "OverUnder": 31.3, "OverPayout": -74, "UnderPayout": -72, "SportsbookId": 14, "OddType": "pregame", "SportsbookUrl": null}, {"GameOddId": 639531, "Sportsbook": "Scrambled", "ScoreId": 17344, "Created": "2020-10-18T12:57:43", "Updated": "2020-10-18T12:59:56", "HomeMoneyLine": -255, "AwayMoneyLine": 204, "DrawMoneyLine": null, "HomePointSpread": -5.1, "AwayPointSpread": 3.5, "HomePointSpreadPayout": -72, "AwayPointSpreadPayout": -77, "OverUnder": 31.3, "OverPayout": -75, "UnderPayout": -74, "SportsbookId": 22, "OddType": "pregame", "SportsbookUrl": null}, {"GameOddId": 639530, "Sportsbook": "Scrambled", "ScoreId": 17344, "Created": "2020-10-18T12:57:41", "Updated": "2020-10-18T12:59:54", "HomeMoneyLine": -245, "AwayMoneyLine": 191, "DrawMoneyLine": null, "HomePointSpread": -5.1, "AwayPointSpread": 3.5, "HomePointSpreadPayout": -72, "AwayPointSpreadPayout": -78, "OverUnder": 31.3, "OverPayout": -75, "UnderPayout": -75, "SportsbookId": 23, "OddType": "pregame", "SportsbookUrl": null}, {"GameOddId": 639160, "Sportsbook": "Scrambled", "ScoreId": 17344, "Created": "2020-10-18T11:32:53", "Updated": "2020-10-18T12:59:55", "HomeMoneyLine": -262, "AwayMoneyLine": 201, "DrawMoneyLine": null, "HomePointSpread": -5.1, "AwayPointSpread": 3.5, "HomePointSpreadPayout": -73, "AwayPointSpreadPayout": -78, "OverUnder": 31.3, "OverPayout": -75, "UnderPayout": -74, "SportsbookId": 25, "OddType": "pregame", "SportsbookUrl": null}], "LiveOdds": [], "AlternateMarketPregameOdds": []}, {"ScoreId": 17345, "Season": 2020, "SeasonType": 1, "Week": 6, "Day": "2020-10-18T00:00:00", "DateTime": "2020-10-18T13:00:00", "Status": "Final", "AwayTeamId": 2, "HomeTeamId": 20, "AwayTeamName": "ATL", "HomeTeamName": "MIN", "GlobalGameId": 17345, "GlobalAwayTeamId": 2, "GlobalHomeTeamId": 20, "HomeTeamScore": 16, "AwayTeamScore": 27, "TotalScore": 43, "HomeRotationNumber": 174, "AwayRotationNumber": 174, "PregameOdds": [{"GameOddId": 639383, "Sportsbook": "Scrambled", "ScoreId": 17345, "Created": "2020-10-18T12:35:11", "Updated": "2020-10-18T12:59:49", "HomeMoneyLine": -127, "AwayMoneyLine": 111, "DrawMoneyLine": null, "HomePointSpread": -2.4, "AwayPointSpread": 1.6, "HomePointSpreadPayout": -75, "AwayPointSpreadPayout": -75, "OverUnder": 36.4, "OverPayout": -75, "UnderPayout": -75, "SportsbookId": 7, "OddType": "pregame", "SportsbookUrl": null}, {"GameOddId": 639405, "Sportsbook": "Scrambled", "ScoreId": 17345, "Created": "2020-10-18T12:42:07", "Updated": "2020-10-18T12:59:50", "HomeMoneyLine": -136, "AwayMoneyLine": 114, "DrawMoneyLine": null, "HomePointSpread": -2.4, "AwayPointSpread": 1.6, "HomePointSpreadPayout": -78, "AwayPointSpreadPayout": -72, "OverUnder": 36.4, "OverPayout": -75, "UnderPayout": -75, "SportsbookId": 8, "OddType": "pregame", "SportsbookUrl": null}, {"GameOddId": 639375, "Sportsbook": "Scrambled", "ScoreId": 17345, "Created": "2020-10-18T12:34:55", "Updated": "2020-10-18T12:59:51", "HomeMoneyLine": -127, "AwayMoneyLine": 111, "DrawMoneyLine": null, "HomePointSpread": -2.4, "AwayPointSpread": 1.6, "HomePointSpreadPayout": -73, "AwayPointSpreadPayout": -73, "OverUnder": 36.4, "OverPayout": -73, "UnderPayout": -73, "SportsbookId": 9, "OddType": "pregame", "SportsbookUrl": null}, {"GameOddId": 639374, "Sportsbook": "Scrambled", "ScoreId": 17345, "Created": "2020-10-18T12:34:54", "Updated": "2020-10-18T12:59:50", "HomeMoneyLine": -127, "AwayMoneyLine": 111, "DrawMoneyLine": null, "HomePointSpread": -2.4, "AwayPointSpread": 1.6, "HomePointSpreadPayout": -73, "AwayPointSpreadPayout": -73, "OverUnder": 36.4, "OverPayout": -73, "UnderPayout": -73, "SportsbookId": 10, "OddType": "pregame", "SportsbookUrl": null}, {"GameOddId": 639377, "Sportsbook": "Scrambled", "ScoreId": 17345, "Created": "2020-10-18T12:34:56", "Updated": "2020-10-18T12:59:52", "HomeMoneyLine": -133, "AwayMoneyLine": 109, "DrawMoneyLine": null, "HomePointSpread": -2.4, "AwayPointSpread": 1.6, "HomePointSpreadPayout": -75, "AwayPointSpreadPayout": -75, "OverUnder": 36.4, "OverPayout": -75, "UnderPayout": -75, "SportsbookId": 12, "OddType": "pregame", "SportsbookUrl": null}, {"GameOddId": 639376, "Sportsbook": "Scrambled", "ScoreId": 17345, "Created": "2020-10-18T12:34:56", "Updated": "2020-10-18T12:59:52", "HomeMoneyLine": -133, "AwayMoneyLine": 109, "DrawMoneyLine": null, "HomePointSpread": -2.4, "AwayPointSpread": 1.6, "HomePointSpreadPayout": -75, "AwayPointSpreadPayout": -75, "OverUnder": 36.4, "OverPayout": -75, "UnderPayout": -75, "SportsbookId": 13, "OddType": "pregame", "SportsbookUrl": null}, {"GameOddId": 639378, "Sportsbook": "Scrambled", "ScoreId": 17345, "Created": "2020-10-18T12:34:57", "Updated": "2020-10-18T12:59:53", "HomeMoneyLine": -127, "AwayMoneyLine": 111, "DrawMoneyLine": null, "HomePointSpread": -2.4, "AwayPointSpread": 1.6, "HomePointSpreadPayout": -73, "AwayPointSpreadPayout": -73, "OverUnder": 36.4, "OverPayout": -73, "UnderPayout": -73, "SportsbookId": 14, "OddType": "pregame", "SportsbookUrl": null}, {"GameOddId": 639507, "Sportsbook": "Scrambled", "ScoreId": 17345, "Created": "2020-10-18T12:54:01", "Updated": "2020-10-18T12:59:56", "HomeMoneyLine": -131, "AwayMoneyLine": 110, "DrawMoneyLine": null, "HomePointSpread": -2.4, "AwayPointSpread": 1.6, "HomePointSpreadPayout": -75, "AwayPointSpreadPayout": -74, "OverUnder": 36.4, "OverPayout": -74, "UnderPayout": -74, "SportsbookId": 22, "OddType": "pregame", "SportsbookUrl": null}, {"GameOddId": 639506, "Sportsbook": "Scrambled", "ScoreId": 17345, "Created": "2020-10-18T12:53:58", "Updated": "2020-10-18T12:59:54", "HomeMoneyLine": -133, "AwayMoneyLine": 112, "DrawMoneyLine": null, "HomePointSpread": -2.4, "AwayPointSpread": 1.6, "HomePointSpreadPayout": -75, "AwayPointSpreadPayout": -75, "OverUnder": 36.1, "OverPayout": -75, "UnderPayout": -75, "SportsbookId": 23, "OddType": "pregame", "SportsbookUrl": null}, {"GameOddId": 639380, "Sportsbook": "Scrambled", "ScoreId": 17345, "Created": "2020-10-18T12:34:58", "Updated": "2020-10-18T12:59:55", "HomeMoneyLine": -133, "AwayMoneyLine": 109, "DrawMoneyLine": null, "HomePointSpread": -2.4, "AwayPointSpread": 1.6, "HomePointSpreadPayout": -75, "AwayPointSpreadPayout": -75, "OverUnder": 36.4, "OverPayout": -75, "UnderPayout": -75, "SportsbookId": 25, "OddType": "pregame", "SportsbookUrl": null}], "LiveOdds": [], "AlternateMarketPregameOdds": []}, {"ScoreId": 17346, "Season": 2020, "SeasonType": 1, "Week": 6, "Day": "2020-10-18T00:00:00", "DateTime": "2020-10-18T13:00:00", "Status": "Final", "AwayTeamId": 35, "HomeTeamId": 23, "AwayTeamName": "WAS", "HomeTeamName": "NYG", "GlobalGameId": 17346, "GlobalAwayTeamId": 35, "GlobalHomeTeamId": 23, "HomeTeamScore": 14, "AwayTeamScore": 13, "TotalScore": 27, "HomeRotationNumber": 177, "AwayRotationNumber": 176, "PregameOdds": [{"GameOddId": 639501, "Sportsbook": "Scrambled", "ScoreId": 17346, "Created": "2020-10-18T12:53:16", "Updated": "2020-10-18T12:59:49", "HomeMoneyLine": -89, "AwayMoneyLine": 78, "DrawMoneyLine": null, "HomePointSpread": -1.4, "AwayPointSpread": 0.9, "HomePointSpreadPayout": -75, "AwayPointSpreadPayout": -75, "OverUnder": 28.6, "OverPayout": -75, "UnderPayout": -75, "SportsbookId": 7, "OddType": "pregame", "SportsbookUrl": null}, {"GameOddId": 639510, "Sportsbook": "Scrambled", "ScoreId": 17346, "Created": "2020-10-18T12:54:34", "Updated": "2020-10-18T12:59:50", "HomeMoneyLine": -89, "AwayMoneyLine": 75, "DrawMoneyLine": null, "HomePointSpread": -1.4, "AwayPointSpread": 0.9, "HomePointSpreadPayout": -75, "AwayPointSpreadPayout": -75, "OverUnder": 28.9, "OverPayout": -72, "UnderPayout": -78, "SportsbookId": 8, "OddType": "pregame", "SportsbookUrl": null}, {"GameOddId": 639490, "Sportsbook": "Scrambled", "ScoreId": 17346, "Created": "2020-10-18T12:52:22", "Updated": "2020-10-18T12:59:51", "HomeMoneyLine": -89, "AwayMoneyLine": 78, "DrawMoneyLine": null, "HomePointSpread": -1.4, "AwayPointSpread": 0.9, "HomePointSpreadPayout": -73, "AwayPointSpreadPayout": -73, "OverUnder": 28.6, "OverPayout": -73, "UnderPayout": -73, "SportsbookId": 9, "OddType": "pregame", "SportsbookUrl": null}, {"GameOddId": 639489, "Sportsbook": "Scrambled", "ScoreId": 17346, "Created": "2020-10-18T12:52:21", "Updated": "2020-10-18T12:59:50", "HomeMoneyLine": -89, "AwayMoneyLine": 78, "DrawMoneyLine": null, "HomePointSpread": -1.4, "AwayPointSpread": 0.9, "HomePointSpreadPayout": -73, "AwayPointSpreadPayout": -73, "OverUnder": 28.6, "OverPayout": -73, "UnderPayout": -73, "SportsbookId": 10, "OddType": "pregame", "SportsbookUrl": null}, {"GameOddId": 639492, "Sportsbook": "Scrambled", "ScoreId": 17346, "Created": "2020-10-18T12:52:24", "Updated": "2020-10-18T12:59:52", "HomeMoneyLine": -93, "AwayMoneyLine": 76, "DrawMoneyLine": null, "HomePointSpread": -1.4, "AwayPointSpread": 0.9, "HomePointSpreadPayout": -75, "AwayPointSpreadPayout": -75, "OverUnder": 28.6, "OverPayout": -75, "UnderPayout": -75, "SportsbookId": 12, "OddType": "pregame", "SportsbookUrl": null}, {"GameOddId": 639491, "Sportsbook": "Scrambled", "ScoreId": 17346, "Created": "2020-10-18T12:52:23", "Updated": "2020-10-18T12:59:52", "HomeMoneyLine": -93, "AwayMoneyLine": 76, "DrawMoneyLine": null, "HomePointSpread": -1.4, "AwayPointSpread": 0.9, "HomePointSpreadPayout": -75, "AwayPointSpreadPayout": -75, "OverUnder": 28.6, "OverPayout": -75, "UnderPayout": -75, "SportsbookId": 13, "OddType": "pregame", "SportsbookUrl": null}, {"GameOddId": 639493, "Sportsbook": "Scrambled", "ScoreId": 17346, "Created": "2020-10-18T12:52:24", "Updated": "2020-10-18T12:59:53", "HomeMoneyLine": -89, "AwayMoneyLine": 78, "DrawMoneyLine": null, "HomePointSpread": -1.4, "AwayPointSpread": 0.9, "HomePointSpreadPayout": -73, "AwayPointSpreadPayout": -73, "OverUnder": 28.6, "OverPayout": -73, "UnderPayout": -73, "SportsbookId": 14, "OddType": "pregame", "SportsbookUrl": null}, {"GameOddId": 639504, "Sportsbook": "Scrambled", "ScoreId": 17346, "Created": "2020-10-18T12:53:24", "Updated": "2020-10-18T12:59:56", "HomeMoneyLine": -90, "AwayMoneyLine": 77, "DrawMoneyLine": null, "HomePointSpread": -1.4, "AwayPointSpread": 0.9, "HomePointSpreadPayout": -74, "AwayPointSpreadPayout": -74, "OverUnder": 28.6, "OverPayout": -74, "UnderPayout": -74, "SportsbookId": 22, "OddType": "pregame", "SportsbookUrl": null}, {"GameOddId": 639548, "Sportsbook": "Scrambled", "ScoreId": 17346, "Created": "2020-10-18T12:59:54", "Updated": "2020-10-18T12:59:54", "HomeMoneyLine": -89, "AwayMoneyLine": 75, "DrawMoneyLine": null, "HomePointSpread": -1.0, "AwayPointSpread": 0.7, "HomePointSpreadPayout": -78, "AwayPointSpreadPayout": -72, "OverUnder": 28.6, "OverPayout": -72, "UnderPayout": -78, "SportsbookId": 23, "OddType": "pregame", "SportsbookUrl": null}, {"GameOddId": 639495, "Sportsbook": "Scrambled", "ScoreId": 17346, "Created": "2020-10-18T12:52:26", "Updated": "2020-10-18T12:59:55", "HomeMoneyLine": -93, "AwayMoneyLine": 76, "DrawMoneyLine": null, "HomePointSpread": -1.4, "AwayPointSpread": 0.9, "HomePointSpreadPayout": -75, "AwayPointSpreadPayout": -75, "OverUnder": 28.6, "OverPayout": -75, "UnderPayout": -75, "SportsbookId": 25, "OddType": "pregame", "SportsbookUrl": null}], "LiveOdds": [], "AlternateMarketPregameOdds": []}, {"ScoreId": 17347, "Season": 2020, "SeasonType": 1, "Week": 6, "Day": "2020-10-18T00:00:00", "DateTime": "2020-10-18T13:00:00", "Status": "Final", "AwayTeamId": 3, "HomeTeamId": 26, "AwayTeamName": "BAL", "HomeTeamName": "PHI", "GlobalGameId": 17347, "GlobalAwayTeamId": 3, "GlobalHomeTeamId": 26, "HomeTeamScore": 19, "AwayTeamScore": 20, "TotalScore": 39, "HomeRotationNumber": 180, "AwayRotationNumber": 179, "PregameOdds": [{"GameOddId": 638643, "Sportsbook": "Scrambled", "ScoreId": 17347, "Created": "2020-10-18T10:05:41", "Updated": "2020-10-18T12:59:49", "HomeMoneyLine": 255, "AwayMoneyLine": -310, "DrawMoneyLine": null, "HomePointSpread": 4.6, "AwayPointSpread": -6.8, "HomePointSpreadPayout": -75, "AwayPointSpreadPayout": -75, "OverUnder": 31.7, "OverPayout": -75, "UnderPayout": -75, "SportsbookId": 7, "OddType": "pregame", "SportsbookUrl": null}, {"GameOddId": 639301, "Sportsbook": "Scrambled", "ScoreId": 17347, "Created": "2020-10-18T12:08:42", "Updated": "2020-10-18T12:59:50", "HomeMoneyLine": 238, "AwayMoneyLine": -313, "DrawMoneyLine": null, "HomePointSpread": 4.6, "AwayPointSpread": -6.8, "HomePointSpreadPayout": -75, "AwayPointSpreadPayout": -75, "OverUnder": 31.7, "OverPayout": -72, "UnderPayout": -78, "SportsbookId": 8, "OddType": "pregame", "SportsbookUrl": null}, {"GameOddId": 638634, "Sportsbook": "Scrambled", "ScoreId": 17347, "Created": "2020-10-18T10:04:28", "Updated": "2020-10-18T12:59:51", "HomeMoneyLine": 255, "AwayMoneyLine": -310, "DrawMoneyLine": null, "HomePointSpread": 4.6, "AwayPointSpread": -6.8, "HomePointSpreadPayout": -73, "AwayPointSpreadPayout": -73, "OverUnder": 31.7, "OverPayout": -73, "UnderPayout": -73, "SportsbookId": 9, "OddType": "pregame", "SportsbookUrl": null}, {"GameOddId": 638633, "Sportsbook": "Scrambled", "ScoreId": 17347, "Created": "2020-10-18T10:04:28", "Updated": "2020-10-18T12:59:50", "HomeMoneyLine": 255, "AwayMoneyLine": -310, "DrawMoneyLine": null, "HomePointSpread": 4.6, "AwayPointSpread": -6.8, "HomePointSpreadPayout": -73, "AwayPointSpreadPayout": -73, "OverUnder": 31.7, "OverPayout": -73, "UnderPayout": -73, "SportsbookId": 10, "OddType": "pregame", "SportsbookUrl": null}, {"GameOddId": 638636, "Sportsbook": "Scrambled", "ScoreId": 17347, "Created": "2020-10-18T10:04:29", "Updated": "2020-10-18T12:59:52", "HomeMoneyLine": 245, "AwayMoneyLine": -340, "DrawMoneyLine": null, "HomePointSpread": 4.6, "AwayPointSpread": -6.8, "HomePointSpreadPayout": -75, "AwayPointSpreadPayout": -75, "OverUnder": 31.7, "OverPayout": -75, "UnderPayout": -75, "SportsbookId": 12, "OddType": "pregame", "SportsbookUrl": null}, {"GameOddId": 638635, "Sportsbook": "Scrambled", "ScoreId": 17347, "Created": "2020-10-18T10:04:29", "Updated": "2020-10-18T12:59:52", "HomeMoneyLine": 245, "AwayMoneyLine": -340, "DrawMoneyLine": null, "HomePointSpread": 4.6, "AwayPointSpread": -6.8, "HomePointSpreadPayout": -75, "AwayPointSpreadPayout": -75, "OverUnder": 31.7, "OverPayout": -75, "UnderPayout": -75, "SportsbookId": 13, "OddType": "pregame", "SportsbookUrl": null}, {"GameOddId": 638637, "Sportsbook": "Scrambled", "ScoreId": 17347, "Created": "2020-10-18T10:04:30", "Updated": "2020-10-18T12:59:53", "HomeMoneyLine": 255, "AwayMoneyLine": -310, "DrawMoneyLine": null, "HomePointSpread": 4.6, "AwayPointSpread": -6.8, "HomePointSpreadPayout": -73, "AwayPointSpreadPayout": -73, "OverUnder": 31.7, "OverPayout": -73, "UnderPayout": -73, "SportsbookId": 14, "OddType": "pregame", "SportsbookUrl": null}, {"GameOddId": 639532, "Sportsbook": "Scrambled", "ScoreId": 17347, "Created": "2020-10-18T12:57:44", "Updated": "2020-10-18T12:59:56", "HomeMoneyLine": 249, "AwayMoneyLine": -320, "DrawMoneyLine": null, "HomePointSpread": 4.6, "AwayPointSpread": -6.8, "HomePointSpreadPayout": -75, "AwayPointSpreadPayout": -74, "OverUnder": 31.7, "OverPayout": -74, "UnderPayout": -75, "SportsbookId": 22, "OddType": "pregame", "SportsbookUrl": null}, {"GameOddId": 639529, "Sportsbook": "Scrambled", "ScoreId": 17347, "Created": "2020-10-18T12:57:41", "Updated": "2020-10-18T12:59:54", "HomeMoneyLine": 238, "AwayMoneyLine": -320, "DrawMoneyLine": null, "HomePointSpread": 4.6, "AwayPointSpread": -6.8, "HomePointSpreadPayout": -78, "AwayPointSpreadPayout": -72, "OverUnder": 31.7, "OverPayout": -75, "UnderPayout": -75, "SportsbookId": 23, "OddType": "pregame", "SportsbookUrl": null}, {"GameOddId": 638638, "Sportsbook": "Scrambled", "ScoreId": 17347, "Created": "2020-10-18T10:04:31", "Updated": "2020-10-18T12:59:55", "HomeMoneyLine": 245, "AwayMoneyLine": -340, "DrawMoneyLine": null, "HomePointSpread": 4.6, "AwayPointSpread": -6.8, "HomePointSpreadPayout": -75, "AwayPointSpreadPayout": -75, "OverUnder": 31.7, "OverPayout": -75, "UnderPayout": -75, "SportsbookId": 25, "OddType": "pregame", "SportsbookUrl": null}], "LiveOdds": [], "AlternateMarketPregameOdds": []}, {"ScoreId": 17348, "Season": 2020, "SeasonType": 1, "Week": 6, "Day": "2020-10-18T00:00:00", "DateTime": "2020-10-18T13:00:00", "Status": "Final", "AwayTeamId": 8, "HomeTeamId": 28, "AwayTeamName": "CLE", "HomeTeamName": "PIT", "GlobalGameId": 17348, "GlobalAwayTeamId": 8, "GlobalHomeTeamId": 28, "HomeTeamScore": 26, "AwayTeamScore": 3, "TotalScore": 31, "HomeRotationNumber": 178, "AwayRotationNumber": 178, "PregameOdds": [{"GameOddId": 639386, "Sportsbook": "Scrambled", "ScoreId": 17348, "Created": "2020-10-18T12:35:30", "Updated": "2020-10-18T12:59:49", "HomeMoneyLine": -119, "AwayMoneyLine": 102, "DrawMoneyLine": null, "HomePointSpread": -2.0, "AwayPointSpread": 1.4, "HomePointSpreadPayout": -75, "AwayPointSpreadPayout": -75, "OverUnder": 34.0, "OverPayout": -75, "UnderPayout": -75, "SportsbookId": 7, "OddType": "pregame", "SportsbookUrl": null}, {"GameOddId": 639539, "Sportsbook": "Scrambled", "ScoreId": 17348, "Created": "2020-10-18T12:58:33", "Updated": "2020-10-18T12:59:50", "HomeMoneyLine": -110, "AwayMoneyLine": 93, "DrawMoneyLine": null, "HomePointSpread": -2.0, "AwayPointSpread": 1.4, "HomePointSpreadPayout": -78, "AwayPointSpreadPayout": -72, "OverUnder": 34.0, "OverPayout": -75, "UnderPayout": -75, "SportsbookId": 8, "OddType": "pregame", "SportsbookUrl": null}, {"GameOddId": 639370, "Sportsbook": "Scrambled", "ScoreId": 17348, "Created": "2020-10-18T12:34:20", "Updated": "2020-10-18T12:59:51", "HomeMoneyLine": -119, "AwayMoneyLine": 102, "DrawMoneyLine": null, "HomePointSpread": -2.0, "AwayPointSpread": 1.4, "HomePointSpreadPayout": -73, "AwayPointSpreadPayout": -73, "OverUnder": 34.0, "OverPayout": -73, "UnderPayout": -73, "SportsbookId": 9, "OddType": "pregame", "SportsbookUrl": null}, {"GameOddId": 639369, "Sportsbook": "Scrambled", "ScoreId": 17348, "Created": "2020-10-18T12:34:20", "Updated": "2020-10-18T12:59:50", "HomeMoneyLine": -119, "AwayMoneyLine": 102, "DrawMoneyLine": null, "HomePointSpread": -2.0, "AwayPointSpread": 1.4, "HomePointSpreadPayout": -73, "AwayPointSpreadPayout": -73, "OverUnder": 34.0, "OverPayout": -73, "UnderPayout": -73, "SportsbookId": 10, "OddType": "pregame", "SportsbookUrl": null}, {"GameOddId": 639364, "Sportsbook": "Scrambled", "ScoreId": 17348, "Created": "2020-10-18T12:34:02", "Updated": "2020-10-18T12:59:52", "HomeMoneyLine": -121, "AwayMoneyLine": 99, "DrawMoneyLine": null, "HomePointSpread": -2.0, "AwayPointSpread": 1.4, "HomePointSpreadPayout": -75, "AwayPointSpreadPayout": -75, "OverUnder": 34.0, "OverPayout": -75, "UnderPayout": -75, "SportsbookId": 12, "OddType": "pregame", "SportsbookUrl": null}, {"GameOddId": 639371, "Sportsbook": "Scrambled", "ScoreId": 17348, "Created": "2020-10-18T12:34:21", "Updated": "2020-10-18T12:59:52", "HomeMoneyLine": -121, "AwayMoneyLine": 99, "DrawMoneyLine": null, "HomePointSpread": -2.0, "AwayPointSpread": 1.4, "HomePointSpreadPayout": -75, "AwayPointSpreadPayout": -75, "OverUnder": 34.0, "OverPayout": -75, "UnderPayout": -75, "SportsbookId": 13, "OddType": "pregame", "SportsbookUrl": null}, {"GameOddId": 639365, "Sportsbook": "Scrambled", "ScoreId": 17348, "Created": "2020-10-18T12:34:03", "Updated": "2020-10-18T12:59:53", "HomeMoneyLine": -119, "AwayMoneyLine": 102, "DrawMoneyLine": null, "HomePointSpread": -2.0, "AwayPointSpread": 1.4, "HomePointSpreadPayout": -73, "AwayPointSpreadPayout": -73, "OverUnder": 34.0, "OverPayout": -73, "UnderPayout": -73, "SportsbookId": 14, "OddType": "pregame", "SportsbookUrl": null}, {"GameOddId": 639543, "Sportsbook": "Scrambled", "ScoreId": 17348, "Created": "2020-10-18T12:58:59", "Updated": "2020-10-18T12:59:56", "HomeMoneyLine": -119, "AwayMoneyLine": 99, "DrawMoneyLine": null, "HomePointSpread": -2.0, "AwayPointSpread": 1.4, "HomePointSpreadPayout": -75, "AwayPointSpreadPayout": -74, "OverUnder": 34.0, "OverPayout": -75, "UnderPayout": -75, "SportsbookId": 22, "OddType": "pregame", "SportsbookUrl": null}, {"GameOddId": 639541, "Sportsbook": "Scrambled", "ScoreId": 17348, "Created": "2020-10-18T12:58:57", "Updated": "2020-10-18T12:59:54", "HomeMoneyLine": -112, "AwayMoneyLine": 95, "DrawMoneyLine": null, "HomePointSpread": -2.0, "AwayPointSpread": 1.4, "HomePointSpreadPayout": -78, "AwayPointSpreadPayout": -72, "OverUnder": 34.0, "OverPayout": -75, "UnderPayout": -75, "SportsbookId": 23, "OddType": "pregame", "SportsbookUrl": null}, {"GameOddId": 639366, "Sportsbook": "Scrambled", "ScoreId": 17348, "Created": "2020-10-18T12:34:05", "Updated": "2020-10-18T12:59:55", "HomeMoneyLine": -121, "AwayMoneyLine": 99, "DrawMoneyLine": null, "HomePointSpread": -2.0, "AwayPointSpread": 1.4, "HomePointSpreadPayout": -75, "AwayPointSpreadPayout": -75, "OverUnder": 34.0, "OverPayout": -75, "UnderPayout": -75, "SportsbookId": 25, "OddType": "pregame", "SportsbookUrl": null}], "LiveOdds": [], "AlternateMarketPregameOdds": []}, {"ScoreId": 17349, "Season": 2020, "SeasonType": 1, "Week": 6, "Day": "2020-10-18T00:00:00", "DateTime": "2020-10-18T13:00:00", "Status": "Final", "AwayTeamId": 6, "HomeTeamId": 5, "AwayTeamName": "CHI", "HomeTeamName": "CAR", "GlobalGameId": 17349, "GlobalAwayTeamId": 6, "GlobalHomeTeamId": 5, "HomeTeamScore": 11, "AwayTeamScore": 16, "TotalScore": 27, "HomeRotationNumber": 172, "AwayRotationNumber": 171, "PregameOdds": [{"GameOddId": 639140, "Sportsbook": "Scrambled", "ScoreId": 17349, "Created": "2020-10-18T11:29:07", "Updated": "2020-10-18T12:59:49", "HomeMoneyLine": -85, "AwayMoneyLine": 75, "DrawMoneyLine": null, "HomePointSpread": -1.4, "AwayPointSpread": 0.9, "HomePointSpreadPayout": -75, "AwayPointSpreadPayout": -75, "OverUnder": 30.6, "OverPayout": -75, "UnderPayout": -75, "SportsbookId": 7, "OddType": "pregame", "SportsbookUrl": null}, {"GameOddId": 639516, "Sportsbook": "Scrambled", "ScoreId": 17349, "Created": "2020-10-18T12:55:47", "Updated": "2020-10-18T12:59:50", "HomeMoneyLine": -83, "AwayMoneyLine": 71, "DrawMoneyLine": null, "HomePointSpread": -1.4, "AwayPointSpread": 0.9, "HomePointSpreadPayout": -72, "AwayPointSpreadPayout": -78, "OverUnder": 30.6, "OverPayout": -75, "UnderPayout": -75, "SportsbookId": 8, "OddType": "pregame", "SportsbookUrl": null}, {"GameOddId": 639126, "Sportsbook": "Scrambled", "ScoreId": 17349, "Created": "2020-10-18T11:28:14", "Updated": "2020-10-18T12:59:51", "HomeMoneyLine": -85, "AwayMoneyLine": 75, "DrawMoneyLine": null, "HomePointSpread": -1.4, "AwayPointSpread": 0.9, "HomePointSpreadPayout": -73, "AwayPointSpreadPayout": -73, "OverUnder": 30.6, "OverPayout": -73, "UnderPayout": -73, "SportsbookId": 9, "OddType": "pregame", "SportsbookUrl": null}, {"GameOddId": 639125, "Sportsbook": "Scrambled", "ScoreId": 17349, "Created": "2020-10-18T11:28:13", "Updated": "2020-10-18T12:59:50", "HomeMoneyLine": -85, "AwayMoneyLine": 75, "DrawMoneyLine": null, "HomePointSpread": -1.4, "AwayPointSpread": 0.9, "HomePointSpreadPayout": -73, "AwayPointSpreadPayout": -73, "OverUnder": 30.6, "OverPayout": -73, "UnderPayout": -73, "SportsbookId": 10, "OddType": "pregame", "SportsbookUrl": null}, {"GameOddId": 639128, "Sportsbook": "Scrambled", "ScoreId": 17349, "Created": "2020-10-18T11:28:15", "Updated": "2020-10-18T12:59:52", "HomeMoneyLine": -89, "AwayMoneyLine": 73, "DrawMoneyLine": null, "HomePointSpread": -1.4, "AwayPointSpread": 0.9, "HomePointSpreadPayout": -75, "AwayPointSpreadPayout": -75, "OverUnder": 30.6, "OverPayout": -75, "UnderPayout": -75, "SportsbookId": 12, "OddType": "pregame", "SportsbookUrl": null}, {"GameOddId": 639127, "Sportsbook": "Scrambled", "ScoreId": 17349, "Created": "2020-10-18T11:28:14", "Updated": "2020-10-18T12:59:52", "HomeMoneyLine": -89, "AwayMoneyLine": 73, "DrawMoneyLine": null, "HomePointSpread": -1.4, "AwayPointSpread": 0.9, "HomePointSpreadPayout": -75, "AwayPointSpreadPayout": -75, "OverUnder": 30.6, "OverPayout": -75, "UnderPayout": -75, "SportsbookId": 13, "OddType": "pregame", "SportsbookUrl": null}, {"GameOddId": 639129, "Sportsbook": "Scrambled", "ScoreId": 17349, "Created": "2020-10-18T11:28:16", "Updated": "2020-10-18T12:59:53", "HomeMoneyLine": -85, "AwayMoneyLine": 75, "DrawMoneyLine": null, "HomePointSpread": -1.4, "AwayPointSpread": 0.9, "HomePointSpreadPayout": -73, "AwayPointSpreadPayout": -73, "OverUnder": 30.6, "OverPayout": -73, "UnderPayout": -73, "SportsbookId": 14, "OddType": "pregame", "SportsbookUrl": null}, {"GameOddId": 639441, "Sportsbook": "Scrambled", "ScoreId": 17349, "Created": "2020-10-18T12:47:40", "Updated": "2020-10-18T12:59:56", "HomeMoneyLine": -86, "AwayMoneyLine": 74, "DrawMoneyLine": null, "HomePointSpread": -1.4, "AwayPointSpread": 0.9, "HomePointSpreadPayout": -74, "AwayPointSpreadPayout": -74, "OverUnder": 30.6, "OverPayout": -75, "UnderPayout": -75, "SportsbookId": 22, "OddType": "pregame", "SportsbookUrl": null}, {"GameOddId": 639446, "Sportsbook": "Scrambled", "ScoreId": 17349, "Created": "2020-10-18T12:48:16", "Updated": "2020-10-18T12:59:54", "HomeMoneyLine": -85, "AwayMoneyLine": 72, "DrawMoneyLine": null, "HomePointSpread": -1.0, "AwayPointSpread": 0.7, "HomePointSpreadPayout": -75, "AwayPointSpreadPayout": -75, "OverUnder": 30.6, "OverPayout": -75, "UnderPayout": -75, "SportsbookId": 23, "OddType": "pregame", "SportsbookUrl": null}, {"GameOddId": 639130, "Sportsbook": "Scrambled", "ScoreId": 17349, "Created": "2020-10-18T11:28:17", "Updated": "2020-10-18T12:59:55", "HomeMoneyLine": -89, "AwayMoneyLine": 73, "DrawMoneyLine": null, "HomePointSpread": -1.4, "AwayPointSpread": 0.9, "HomePointSpreadPayout": -75, "AwayPointSpreadPayout": -75, "OverUnder": 30.6, "OverPayout": -75, "UnderPayout": -75, "SportsbookId": 25, "OddType": "pregame", "SportsbookUrl": null}], "LiveOdds": [], "AlternateMarketPregameOdds": []}, {"ScoreId": 17350, "Season": 2020, "SeasonType": 1, "Week": 6, "Day": "2020-10-18T00:00:00", "DateTime": "2020-10-18T13:00:00", "Status": "Final", "AwayTeamId": 11, "HomeTeamId": 15, "AwayTeamName": "DET", "HomeTeamName": "JAX", "GlobalGameId": 17350, "GlobalAwayTeamId": 11, "GlobalHomeTeamId": 15, "HomeTeamScore": 11, "AwayTeamScore": 23, "TotalScore": 34, "HomeRotationNumber": 173, "AwayRotationNumber": 172, "PregameOdds": [{"GameOddId": 638946, "Sportsbook": "Scrambled", "ScoreId": 17350, "Created": "2020-10-18T11:07:20", "Updated": "2020-10-18T12:59:49", "HomeMoneyLine": 101, "AwayMoneyLine": -114, "DrawMoneyLine": null, "HomePointSpread": 1.4, "AwayPointSpread": -2.0, "HomePointSpreadPayout": -75, "AwayPointSpreadPayout": -75, "OverUnder": 36.1, "OverPayout": -75, "UnderPayout": -75, "SportsbookId": 7, "OddType": "pregame", "SportsbookUrl": null}, {"GameOddId": 639343, "Sportsbook": "Scrambled", "ScoreId": 17350, "Created": "2020-10-18T12:29:22", "Updated": "2020-10-18T12:59:50", "HomeMoneyLine": 93, "AwayMoneyLine": -110, "DrawMoneyLine": null, "HomePointSpread": 1.4, "AwayPointSpread": -2.0, "HomePointSpreadPayout": -75, "AwayPointSpreadPayout": -75, "OverUnder": 35.8, "OverPayout": -75, "UnderPayout": -75, "SportsbookId": 8, "OddType": "pregame", "SportsbookUrl": null}, {"GameOddId": 638940, "Sportsbook": "Scrambled", "ScoreId": 17350, "Created": "2020-10-18T11:07:03", "Updated": "2020-10-18T12:59:51", "HomeMoneyLine": 101, "AwayMoneyLine": -114, "DrawMoneyLine": null, "HomePointSpread": 1.4, "AwayPointSpread": -2.0, "HomePointSpreadPayout": -73, "AwayPointSpreadPayout": -73, "OverUnder": 36.1, "OverPayout": -73, "UnderPayout": -73, "SportsbookId": 9, "OddType": "pregame", "SportsbookUrl": null}, {"GameOddId": 638939, "Sportsbook": "Scrambled", "ScoreId": 17350, "Created": "2020-10-18T11:07:02", "Updated": "2020-10-18T12:59:50", "HomeMoneyLine": 101, "AwayMoneyLine": -114, "DrawMoneyLine": null, "HomePointSpread": 1.4, "AwayPointSpread": -2.0, "HomePointSpreadPayout": -73, "AwayPointSpreadPayout": -73, "OverUnder": 36.1, "OverPayout": -73, "UnderPayout": -73, "SportsbookId": 10, "OddType": "pregame", "SportsbookUrl": null}, {"GameOddId": 638942, "Sportsbook": "Scrambled", "ScoreId": 17350, "Created": "2020-10-18T11:07:04", "Updated": "2020-10-18T12:59:52", "HomeMoneyLine": 97, "AwayMoneyLine": -121, "DrawMoneyLine": null, "HomePointSpread": 1.4, "AwayPointSpread": -2.0, "HomePointSpreadPayout": -75, "AwayPointSpreadPayout": -75, "OverUnder": 36.1, "OverPayout": -75, "UnderPayout": -75, "SportsbookId": 12, "OddType": "pregame", "SportsbookUrl": null}, {"GameOddId": 638941, "Sportsbook": "Scrambled", "ScoreId": 17350, "Created": "2020-10-18T11:07:03", "Updated": "2020-10-18T12:59:52", "HomeMoneyLine": 97, "AwayMoneyLine": -121, "DrawMoneyLine": null, "HomePointSpread": 1.4, "AwayPointSpread": -2.0, "HomePointSpreadPayout": -75, "AwayPointSpreadPayout": -75, "OverUnder": 36.1, "OverPayout": -75, "UnderPayout": -75, "SportsbookId": 13, "OddType": "pregame", "SportsbookUrl": null}, {"GameOddId": 638943, "Sportsbook": "Scrambled", "ScoreId": 17350, "Created": "2020-10-18T11:07:05", "Updated": "2020-10-18T12:59:53", "HomeMoneyLine": 101, "AwayMoneyLine": -114, "DrawMoneyLine": null, "HomePointSpread": 1.4, "AwayPointSpread": -2.0, "HomePointSpreadPayout": -73, "AwayPointSpreadPayout": -73, "OverUnder": 36.1, "OverPayout": -73, "UnderPayout": -73, "SportsbookId": 14, "OddType": "pregame", "SportsbookUrl": null}, {"GameOddId": 639043, "Sportsbook": "Scrambled", "ScoreId": 17350, "Created": "2020-10-18T11:21:25", "Updated": "2020-10-18T12:59:56", "HomeMoneyLine": 98, "AwayMoneyLine": -116, "DrawMoneyLine": null, "HomePointSpread": 1.4, "AwayPointSpread": -2.0, "HomePointSpreadPayout": -75, "AwayPointSpreadPayout": -75, "OverUnder": 36.1, "OverPayout": -74, "UnderPayout": -74, "SportsbookId": 22, "OddType": "pregame", "SportsbookUrl": null}, {"GameOddId": 638682, "Sportsbook": "Scrambled", "ScoreId": 17350, "Created": "2020-10-18T10:09:48", "Updated": "2020-10-18T12:59:54", "HomeMoneyLine": 92, "AwayMoneyLine": -109, "DrawMoneyLine": null, "HomePointSpread": 1.4, "AwayPointSpread": -2.0, "HomePointSpreadPayout": -75, "AwayPointSpreadPayout": -75, "OverUnder": 36.4, "OverPayout": -75, "UnderPayout": -75, "SportsbookId": 23, "OddType": "pregame", "SportsbookUrl": null}, {"GameOddId": 638944, "Sportsbook": "Scrambled", "ScoreId": 17350, "Created": "2020-10-18T11:07:06", "Updated": "2020-10-18T12:59:55", "HomeMoneyLine": 97, "AwayMoneyLine": -121, "DrawMoneyLine": null, "HomePointSpread": 1.4, "AwayPointSpread": -2.0, "HomePointSpreadPayout": -75, "AwayPointSpreadPayout": -75, "OverUnder": 36.1, "OverPayout": -75, "UnderPayout": -75, "SportsbookId": 25, "OddType": "pregame", "SportsbookUrl": null}], "LiveOdds": [], "AlternateMarketPregameOdds": []}, {"ScoreId": 17578, "Season": 2020, "SeasonType": 1, "Week": 6, "Day": "2020-10-18T00:00:00", "DateTime": "2020-10-18T14:00:00", "Status": "Final", "AwayTeamId": 10, "HomeTeamId": 21, "AwayTeamName": "DEN", "HomeTeamName": "NE", "GlobalGameId": 17578, "GlobalAwayTeamId": 10, "GlobalHomeTeamId": 21, "HomeTeamScore": 6, "AwayTeamScore": 12, "TotalScore": 20, "HomeRotationNumber": 192, "AwayRotationNumber": 191, "PregameOdds": [{"GameOddId": 639280, "Sportsbook": "Scrambled", "ScoreId": 17578, "Created": "2020-10-18T12:02:20", "Updated": "2020-10-18T12:59:49", "HomeMoneyLine": -235, "AwayMoneyLine": 201, "DrawMoneyLine": null, "HomePointSpread": -4.8, "AwayPointSpread": 3.2, "HomePointSpreadPayout": -75, "AwayPointSpreadPayout": -75, "OverUnder": 30.0, "OverPayout": -75, "UnderPayout": -75, "SportsbookId": 7, "OddType": "pregame", "SportsbookUrl": null}, {"GameOddId": 639535, "Sportsbook": "Scrambled", "ScoreId": 17578, "Created": "2020-10-18T12:58:14", "Updated": "2020-10-18T12:59:50", "HomeMoneyLine": -245, "AwayMoneyLine": 197, "DrawMoneyLine": null, "HomePointSpread": -4.8, "AwayPointSpread": 3.2, "HomePointSpreadPayout": -75, "AwayPointSpreadPayout": -75, "OverUnder": 29.6, "OverPayout": -78, "UnderPayout": -72, "SportsbookId": 8, "OddType": "pregame", "SportsbookUrl": null}, {"GameOddId": 639269, "Sportsbook": "Scrambled", "ScoreId": 17578, "Created": "2020-10-18T12:01:09", "Updated": "2020-10-18T12:59:51", "HomeMoneyLine": -235, "AwayMoneyLine": 201, "DrawMoneyLine": null, "HomePointSpread": -4.8, "AwayPointSpread": 3.2, "HomePointSpreadPayout": -73, "AwayPointSpreadPayout": -73, "OverUnder": 30.0, "OverPayout": -73, "UnderPayout": -73, "SportsbookId": 9, "OddType": "pregame", "SportsbookUrl": null}, {"GameOddId": 639268, "Sportsbook": "Scrambled", "ScoreId": 17578, "Created": "2020-10-18T12:01:08", "Updated": "2020-10-18T12:59:50", "HomeMoneyLine": -235, "AwayMoneyLine": 201, "DrawMoneyLine": null, "HomePointSpread": -4.8, "AwayPointSpread": 3.2, "HomePointSpreadPayout": -73, "AwayPointSpreadPayout": -73, "OverUnder": 30.0, "OverPayout": -73, "UnderPayout": -73, "SportsbookId": 10, "OddType": "pregame", "SportsbookUrl": null}, {"GameOddId": 639271, "Sportsbook": "Scrambled", "ScoreId": 17578, "Created": "2020-10-18T12:01:10", "Updated": "2020-10-18T12:59:52", "HomeMoneyLine": -255, "AwayMoneyLine": 194, "DrawMoneyLine": null, "HomePointSpread": -4.8, "AwayPointSpread": 3.2, "HomePointSpreadPayout": -75, "AwayPointSpreadPayout": -75, "OverUnder": 30.0, "OverPayout": -75, "UnderPayout": -75, "SportsbookId": 12, "OddType": "pregame", "SportsbookUrl": null}, {"GameOddId": 639270, "Sportsbook": "Scrambled", "ScoreId": 17578, "Created": "2020-10-18T12:01:09", "Updated": "2020-10-18T12:59:52", "HomeMoneyLine": -255, "AwayMoneyLine": 194, "DrawMoneyLine": null, "HomePointSpread": -4.8, "AwayPointSpread": 3.2, "HomePointSpreadPayout": -75, "AwayPointSpreadPayout": -75, "OverUnder": 30.0, "OverPayout": -75, "UnderPayout": -75, "SportsbookId": 13, "OddType": "pregame", "SportsbookUrl": null}, {"GameOddId": 639272, "Sportsbook": "Scrambled", "ScoreId": 17578, "Created": "2020-10-18T12:01:11", "Updated": "2020-10-18T12:59:53", "HomeMoneyLine": -235, "AwayMoneyLine": 201, "DrawMoneyLine": null, "HomePointSpread": -4.8, "AwayPointSpread": 3.2, "HomePointSpreadPayout": -73, "AwayPointSpreadPayout": -73, "OverUnder": 30.0, "OverPayout": -73, "UnderPayout": -73, "SportsbookId": 14, "OddType": "pregame", "SportsbookUrl": null}, {"GameOddId": 639537, "Sportsbook": "Scrambled", "ScoreId": 17578, "Created": "2020-10-18T12:58:20", "Updated": "2020-10-18T12:59:56", "HomeMoneyLine": -242, "AwayMoneyLine": 197, "DrawMoneyLine": null, "HomePointSpread": -4.8, "AwayPointSpread": 3.2, "HomePointSpreadPayout": -75, "AwayPointSpreadPayout": -75, "OverUnder": 30.0, "OverPayout": -74, "UnderPayout": -74, "SportsbookId": 22, "OddType": "pregame", "SportsbookUrl": null}, {"GameOddId": 639443, "Sportsbook": "Scrambled", "ScoreId": 17578, "Created": "2020-10-18T12:47:56", "Updated": "2020-10-18T12:59:54", "HomeMoneyLine": -238, "AwayMoneyLine": 184, "DrawMoneyLine": null, "HomePointSpread": -4.8, "AwayPointSpread": 3.2, "HomePointSpreadPayout": -75, "AwayPointSpreadPayout": -75, "OverUnder": 30.0, "OverPayout": -75, "UnderPayout": -75, "SportsbookId": 23, "OddType": "pregame", "SportsbookUrl": null}, {"GameOddId": 639266, "Sportsbook": "Scrambled", "ScoreId": 17578, "Created": "2020-10-18T12:00:53", "Updated": "2020-10-18T12:59:55", "HomeMoneyLine": -255, "AwayMoneyLine": 194, "DrawMoneyLine": null, "HomePointSpread": -4.8, "AwayPointSpread": 3.2, "HomePointSpreadPayout": -75, "AwayPointSpreadPayout": -75, "OverUnder": 30.0, "OverPayout": -75, "UnderPayout": -75, "SportsbookId": 25, "OddType": "pregame", "SportsbookUrl": null}], "LiveOdds": [], "AlternateMarketPregameOdds": []}, {"ScoreId": 17351, "Season": 2020, "SeasonType": 1, "Week": 6, "Day": "2020-10-18T00:00:00", "DateTime": "2020-10-18T16:05:00", "Status": "Postponed", "AwayTeamId": 19, "HomeTeamId": 10, "AwayTeamName": "MIA", "HomeTeamName": "DEN", "GlobalGameId": 17351, "GlobalAwayTeamId": 19, "GlobalHomeTeamId": 10, "HomeTeamScore": null, "AwayTeamScore": null, "TotalScore": 0, "HomeRotationNumber": 184, "AwayRotationNumber": 183, "PregameOdds": [{"GameOddId": 498521, "Sportsbook": "Scrambled", "ScoreId": 17351, "Created": "2020-05-11T18:31:38", "Updated": "2020-09-08T21:52:33", "HomeMoneyLine": null, "AwayMoneyLine": null, "DrawMoneyLine": null, "HomePointSpread": -3.7, "AwayPointSpread": 2.6, "HomePointSpreadPayout": -75, "AwayPointSpreadPayout": -75, "OverUnder": null, "OverPayout": null, "UnderPayout": null, "SportsbookId": 7, "OddType": "pregame", "SportsbookUrl": null}, {"GameOddId": 608953, "Sportsbook": "Scrambled", "ScoreId": 17351, "Created": "2020-10-10T09:43:47", "Updated": "2020-10-11T08:59:51", "HomeMoneyLine": -86, "AwayMoneyLine": 74, "DrawMoneyLine": null, "HomePointSpread": -0.7, "AwayPointSpread": 0.5, "HomePointSpreadPayout": -78, "AwayPointSpreadPayout": -72, "OverUnder": null, "OverPayout": null, "UnderPayout": null, "SportsbookId": 8, "OddType": "pregame", "SportsbookUrl": null}, {"GameOddId": 498668, "Sportsbook": "Scrambled", "ScoreId": 17351, "Created": "2020-05-11T18:42:34", "Updated": "2020-09-08T21:51:55", "HomeMoneyLine": null, "AwayMoneyLine": null, "DrawMoneyLine": null, "HomePointSpread": -3.7, "AwayPointSpread": 2.6, "HomePointSpreadPayout": -75, "AwayPointSpreadPayout": -75, "OverUnder": null, "OverPayout": null, "UnderPayout": null, "SportsbookId": 9, "OddType": "pregame", "SportsbookUrl": null}, {"GameOddId": 498611, "Sportsbook": "Scrambled", "ScoreId": 17351, "Created": "2020-05-11T18:42:25", "Updated": "2020-09-08T21:52:15", "HomeMoneyLine": null, "AwayMoneyLine": null, "DrawMoneyLine": null, "HomePointSpread": -3.7, "AwayPointSpread": 2.6, "HomePointSpreadPayout": -75, "AwayPointSpreadPayout": -75, "OverUnder": null, "OverPayout": null, "UnderPayout": null, "SportsbookId": 10, "OddType": "pregame", "SportsbookUrl": null}, {"GameOddId": 498782, "Sportsbook": "Scrambled", "ScoreId": 17351, "Created": "2020-05-11T18:42:57", "Updated": "2020-09-08T21:51:36", "HomeMoneyLine": null, "AwayMoneyLine": null, "DrawMoneyLine": null, "HomePointSpread": -3.7, "AwayPointSpread": 2.6, "HomePointSpreadPayout": -75, "AwayPointSpreadPayout": -75, "OverUnder": null, "OverPayout": null, "UnderPayout": null, "SportsbookId": 12, "OddType": "pregame", "SportsbookUrl": null}, {"GameOddId": 498725, "Sportsbook": "Scrambled", "ScoreId": 17351, "Created": "2020-05-11T18:42:51", "Updated": "2020-09-08T21:51:56", "HomeMoneyLine": null, "AwayMoneyLine": null, "DrawMoneyLine": null, "HomePointSpread": -3.7, "AwayPointSpread": 2.6, "HomePointSpreadPayout": -75, "AwayPointSpreadPayout": -75, "OverUnder": null, "OverPayout": null, "UnderPayout": null, "SportsbookId": 13, "OddType": "pregame", "SportsbookUrl": null}, {"GameOddId": 498839, "Sportsbook": "Scrambled", "ScoreId": 17351, "Created": "2020-05-11T18:43:09", "Updated": "2020-09-08T21:51:37", "HomeMoneyLine": null, "AwayMoneyLine": null, "DrawMoneyLine": null, "HomePointSpread": -3.7, "AwayPointSpread": 2.6, "HomePointSpreadPayout": -75, "AwayPointSpreadPayout": -75, "OverUnder": null, "OverPayout": null, "UnderPayout": null, "SportsbookId": 14, "OddType": "pregame", "SportsbookUrl": null}, {"GameOddId": 498984, "Sportsbook": "Scrambled", "ScoreId": 17351, "Created": "2020-05-11T18:45:50", "Updated": "2020-10-18T16:04:41", "HomeMoneyLine": null, "AwayMoneyLine": null, "DrawMoneyLine": null, "HomePointSpread": -3.7, "AwayPointSpread": 2.6, "HomePointSpreadPayout": -75, "AwayPointSpreadPayout": -75, "OverUnder": null, "OverPayout": null, "UnderPayout": null, "SportsbookId": 22, "OddType": "pregame", "SportsbookUrl": null}, {"GameOddId": 498928, "Sportsbook": "Scrambled", "ScoreId": 17351, "Created": "2020-05-11T18:43:30", "Updated": "2020-09-08T21:51:39", "HomeMoneyLine": null, "AwayMoneyLine": null, "DrawMoneyLine": null, "HomePointSpread": -3.7, "AwayPointSpread": 2.6, "HomePointSpreadPayout": -75, "AwayPointSpreadPayout": -75, "OverUnder": null, "OverPayout": null, "UnderPayout": null, "SportsbookId": 25, "OddType": "pregame", "SportsbookUrl": null}], "LiveOdds": [], "AlternateMarketPregameOdds": []}, {"ScoreId": 17352, "Season": 2020, "SeasonType": 1, "Week": 6, "Day": "2020-10-18T00:00:00", "DateTime": "2020-10-18T16:05:00", "Status": "Postponed", "AwayTeamId": 24, "HomeTeamId": 29, "AwayTeamName": "NYJ", "HomeTeamName": "LAC", "GlobalGameId": 17352, "GlobalAwayTeamId": 24, "GlobalHomeTeamId": 29, "HomeTeamScore": null, "AwayTeamScore": null, "TotalScore": 0, "HomeRotationNumber": 183, "AwayRotationNumber": 182, "PregameOdds": [{"GameOddId": 498522, "Sportsbook": "Scrambled", "ScoreId": 17352, "Created": "2020-05-11T18:31:38", "Updated": "2020-09-13T13:55:39", "HomeMoneyLine": null, "AwayMoneyLine": null, "DrawMoneyLine": null, "HomePointSpread": -3.7, "AwayPointSpread": 2.6, "HomePointSpreadPayout": -75, "AwayPointSpreadPayout": -75, "OverUnder": null, "OverPayout": null, "UnderPayout": null, "SportsbookId": 7, "OddType": "pregame", "SportsbookUrl": null}, {"GameOddId": 606395, "Sportsbook": "Scrambled", "ScoreId": 17352, "Created": "2020-10-08T20:33:38", "Updated": "2020-10-09T09:59:23", "HomeMoneyLine": -232, "AwayMoneyLine": 187, "DrawMoneyLine": null, "HomePointSpread": -5.4, "AwayPointSpread": 3.7, "HomePointSpreadPayout": -75, "AwayPointSpreadPayout": -75, "OverUnder": null, "OverPayout": null, "UnderPayout": null, "SportsbookId": 8, "OddType": "pregame", "SportsbookUrl": null}, {"GameOddId": 498667, "Sportsbook": "Scrambled", "ScoreId": 17352, "Created": "2020-05-11T18:42:34", "Updated": "2020-09-13T13:55:08", "HomeMoneyLine": null, "AwayMoneyLine": null, "DrawMoneyLine": null, "HomePointSpread": -3.7, "AwayPointSpread": 2.6, "HomePointSpreadPayout": -75, "AwayPointSpreadPayout": -75, "OverUnder": null, "OverPayout": null, "UnderPayout": null, "SportsbookId": 9, "OddType": "pregame", "SportsbookUrl": null}, {"GameOddId": 498610, "Sportsbook": "Scrambled", "ScoreId": 17352, "Created": "2020-05-11T18:42:25", "Updated": "2020-09-13T13:55:07", "HomeMoneyLine": null, "AwayMoneyLine": null, "DrawMoneyLine": null, "HomePointSpread": -3.7, "AwayPointSpread": 2.6, "HomePointSpreadPayout": -75, "AwayPointSpreadPayout": -75, "OverUnder": null, "OverPayout": null, "UnderPayout": null, "SportsbookId": 10, "OddType": "pregame", "SportsbookUrl": null}, {"GameOddId": 498781, "Sportsbook": "Scrambled", "ScoreId": 17352, "Created": "2020-05-11T18:42:57", "Updated": "2020-09-13T13:55:11", "HomeMoneyLine": null, "AwayMoneyLine": null, "DrawMoneyLine": null, "HomePointSpread": -3.7, "AwayPointSpread": 2.6, "HomePointSpreadPayout": -75, "AwayPointSpreadPayout": -75, "OverUnder": null, "OverPayout": null, "UnderPayout": null, "SportsbookId": 12, "OddType": "pregame", "SportsbookUrl": null}, {"GameOddId": 498724, "Sportsbook": "Scrambled", "ScoreId": 17352, "Created": "2020-05-11T18:42:51", "Updated": "2020-09-13T13:55:10", "HomeMoneyLine": null, "AwayMoneyLine": null, "DrawMoneyLine": null, "HomePointSpread": -3.7, "AwayPointSpread": 2.6, "HomePointSpreadPayout": -75, "AwayPointSpreadPayout": -75, "OverUnder": null, "OverPayout": null, "UnderPayout": null, "SportsbookId": 13, "OddType": "pregame", "SportsbookUrl": null}, {"GameOddId": 498838, "Sportsbook": "Scrambled", "ScoreId": 17352, "Created": "2020-05-11T18:43:09", "Updated": "2020-09-13T13:55:12", "HomeMoneyLine": null, "AwayMoneyLine": null, "DrawMoneyLine": null, "HomePointSpread": -3.7, "AwayPointSpread": 2.6, "HomePointSpreadPayout": -75, "AwayPointSpreadPayout": -75, "OverUnder": null, "OverPayout": null, "UnderPayout": null, "SportsbookId": 14, "OddType": "pregame", "SportsbookUrl": null}, {"GameOddId": 498985, "Sportsbook": "Scrambled", "ScoreId": 17352, "Created": "2020-05-11T18:45:50", "Updated": "2020-10-18T16:04:41", "HomeMoneyLine": null, "AwayMoneyLine": null, "DrawMoneyLine": null, "HomePointSpread": -3.7, "AwayPointSpread": 2.6, "HomePointSpreadPayout": -75, "AwayPointSpreadPayout": -75, "OverUnder": null, "OverPayout": null, "UnderPayout": null, "SportsbookId": 22, "OddType": "pregame", "SportsbookUrl": null}, {"GameOddId": 498927, "Sportsbook": "Scrambled", "ScoreId": 17352, "Created": "2020-05-11T18:43:30", "Updated": "2020-09-13T13:55:14", "HomeMoneyLine": null, "AwayMoneyLine": null, "DrawMoneyLine": null, "HomePointSpread": -3.7, "AwayPointSpread": 2.6, "HomePointSpreadPayout": -75, "AwayPointSpreadPayout": -75, "OverUnder": null, "OverPayout": null, "UnderPayout": null, "SportsbookId": 25, "OddType": "pregame", "SportsbookUrl": null}], "LiveOdds": [], "AlternateMarketPregameOdds": []}, {"ScoreId": 17639, "Season": 2020, "SeasonType": 1, "Week": 6, "Day": "2020-10-18T00:00:00", "DateTime": "2020-10-18T16:05:00", "Status": "Final", "AwayTeamId": 24, "HomeTeamId": 19, "AwayTeamName": "NYJ", "HomeTeamName": "MIA", "GlobalGameId": 17639, "GlobalAwayTeamId": 24, "GlobalHomeTeamId": 19, "HomeTeamScore": 16, "AwayTeamScore": 0, "TotalScore": 16, "HomeRotationNumber": 191, "AwayRotationNumber": 190, "PregameOdds": [{"GameOddId": 648982, "Sportsbook": "Scrambled", "ScoreId": 17639, "Created": "2020-10-18T16:04:26", "Updated": "2020-10-18T16:04:56", "HomeMoneyLine": -255, "AwayMoneyLine": 211, "DrawMoneyLine": null, "HomePointSpread": -5.8, "AwayPointSpread": 3.9, "HomePointSpreadPayout": -80, "AwayPointSpreadPayout": -72, "OverUnder": 31.7, "OverPayout": -78, "UnderPayout": -73, "SportsbookId": 7, "OddType": "pregame", "SportsbookUrl": null}, {"GameOddId": 648343, "Sportsbook": "Scrambled", "ScoreId": 17639, "Created": "2020-10-18T15:50:35", "Updated": "2020-10-18T16:04:57", "HomeMoneyLine": -286, "AwayMoneyLine": 225, "DrawMoneyLine": null, "HomePointSpread": -5.8, "AwayPointSpread": 3.9, "HomePointSpreadPayout": -75, "AwayPointSpreadPayout": -75, "OverUnder": 31.3, "OverPayout": -75, "UnderPayout": -75, "SportsbookId": 8, "OddType": "pregame", "SportsbookUrl": null}, {"GameOddId": 649000, "Sportsbook": "Scrambled", "ScoreId": 17639, "Created": "2020-10-18T16:04:59", "Updated": "2020-10-18T16:04:59", "HomeMoneyLine": null, "AwayMoneyLine": null, "DrawMoneyLine": null, "HomePointSpread": -5.8, "AwayPointSpread": 3.9, "HomePointSpreadPayout": -77, "AwayPointSpreadPayout": -70, "OverUnder": 35.8, "OverPayout": 119, "UnderPayout": -146, "SportsbookId": 9, "OddType": "pregame", "SportsbookUrl": null}, {"GameOddId": 648999, "Sportsbook": "Scrambled", "ScoreId": 17639, "Created": "2020-10-18T16:04:58", "Updated": "2020-10-18T16:04:58", "HomeMoneyLine": null, "AwayMoneyLine": null, "DrawMoneyLine": null, "HomePointSpread": -5.8, "AwayPointSpread": 3.9, "HomePointSpreadPayout": -77, "AwayPointSpreadPayout": -70, "OverUnder": 35.8, "OverPayout": 119, "UnderPayout": -146, "SportsbookId": 10, "OddType": "pregame", "SportsbookUrl": null}, {"GameOddId": 648944, "Sportsbook": "Scrambled", "ScoreId": 17639, "Created": "2020-10-18T16:03:23", "Updated": "2020-10-18T16:04:36", "HomeMoneyLine": -272, "AwayMoneyLine": 211, "DrawMoneyLine": null, "HomePointSpread": -5.8, "AwayPointSpread": 3.9, "HomePointSpreadPayout": -80, "AwayPointSpreadPayout": -72, "OverUnder": 31.7, "OverPayout": -78, "UnderPayout": -73, "SportsbookId": 12, "OddType": "pregame", "SportsbookUrl": null}, {"GameOddId": 648943, "Sportsbook": "Scrambled", "ScoreId": 17639, "Created": "2020-10-18T16:03:22", "Updated": "2020-10-18T16:04:32", "HomeMoneyLine": -272, "AwayMoneyLine": 211, "DrawMoneyLine": null, "HomePointSpread": -5.8, "AwayPointSpread": 3.9, "HomePointSpreadPayout": -80, "AwayPointSpreadPayout": -72, "OverUnder": 31.7, "OverPayout": -78, "UnderPayout": -73, "SportsbookId": 13, "OddType": "pregame", "SportsbookUrl": null}, {"GameOddId": 648945, "Sportsbook": "Scrambled", "ScoreId": 17639, "Created": "2020-10-18T16:03:25", "Updated": "2020-10-18T16:04:38", "HomeMoneyLine": -255, "AwayMoneyLine": 211, "DrawMoneyLine": null, "HomePointSpread": -5.8, "AwayPointSpread": 3.9, "HomePointSpreadPayout": -77, "AwayPointSpreadPayout": -70, "OverUnder": 31.7, "OverPayout": -75, "UnderPayout": -71, "SportsbookId": 14, "OddType": "pregame", "SportsbookUrl": null}, {"GameOddId": 648993, "Sportsbook": "Scrambled", "ScoreId": 17639, "Created": "2020-10-18T16:04:41", "Updated": "2020-10-18T16:04:41", "HomeMoneyLine": -263, "AwayMoneyLine": 211, "DrawMoneyLine": null, "HomePointSpread": -5.8, "AwayPointSpread": 3.9, "HomePointSpreadPayout": -78, "AwayPointSpreadPayout": -72, "OverUnder": 31.7, "OverPayout": -77, "UnderPayout": -72, "SportsbookId": 22, "OddType": "pregame", "SportsbookUrl": null}, {"GameOddId": 648992, "Sportsbook": "Scrambled", "ScoreId": 17639, "Created": "2020-10-18T16:04:39", "Updated": "2020-10-18T16:04:39", "HomeMoneyLine": -259, "AwayMoneyLine": 197, "DrawMoneyLine": null, "HomePointSpread": -5.8, "AwayPointSpread": 3.9, "HomePointSpreadPayout": -78, "AwayPointSpreadPayout": -72, "OverUnder": 32.0, "OverPayout": -75, "UnderPayout": -75, "SportsbookId": 23, "OddType": "pregame", "SportsbookUrl": null}, {"GameOddId": 648947, "Sportsbook": "Scrambled", "ScoreId": 17639, "Created": "2020-10-18T16:03:27", "Updated": "2020-10-18T16:04:40", "HomeMoneyLine": -272, "AwayMoneyLine": 211, "DrawMoneyLine": null, "HomePointSpread": -5.8, "AwayPointSpread": 3.9, "HomePointSpreadPayout": -80, "AwayPointSpreadPayout": -72, "OverUnder": 31.7, "OverPayout": -78, "UnderPayout": -73, "SportsbookId": 25, "OddType": "pregame", "SportsbookUrl": null}], "LiveOdds": [], "AlternateMarketPregameOdds": []}, {"ScoreId": 17353, "Season": 2020, "SeasonType": 1, "Week": 6, "Day": "2020-10-18T00:00:00", "DateTime": "2020-10-18T16:25:00", "Status": "Final", "AwayTeamId": 12, "HomeTeamId": 33, "AwayTeamName": "GB", "HomeTeamName": "TB", "GlobalGameId": 17353, "GlobalAwayTeamId": 12, "GlobalHomeTeamId": 33, "HomeTeamScore": 26, "AwayTeamScore": 5, "TotalScore": 33, "HomeRotationNumber": 185, "AwayRotationNumber": 185, "PregameOdds": [{"GameOddId": 649411, "Sportsbook": "Scrambled", "ScoreId": 17353, "Created": "2020-10-18T16:21:11", "Updated": "2020-10-18T16:24:21", "HomeMoneyLine": 89, "AwayMoneyLine": -101, "DrawMoneyLine": null, "HomePointSpread": 1.4, "AwayPointSpread": -2.0, "HomePointSpreadPayout": -82, "AwayPointSpreadPayout": -70, "OverUnder": 37.5, "OverPayout": -75, "UnderPayout": -75, "SportsbookId": 7, "OddType": "pregame", "SportsbookUrl": null}, {"GameOddId": 649356, "Sportsbook": "Scrambled", "ScoreId": 17353, "Created": "2020-10-18T16:17:34", "Updated": "2020-10-18T16:24:47", "HomeMoneyLine": 87, "AwayMoneyLine": -104, "DrawMoneyLine": null, "HomePointSpread": 1.2, "AwayPointSpread": -1.7, "HomePointSpreadPayout": 68, "AwayPointSpreadPayout": -82, "OverUnder": 37.1, "OverPayout": -78, "UnderPayout": -72, "SportsbookId": 8, "OddType": "pregame", "SportsbookUrl": null}, {"GameOddId": 649489, "Sportsbook": "Scrambled", "ScoreId": 17353, "Created": "2020-10-18T16:24:48", "Updated": "2020-10-18T16:24:48", "HomeMoneyLine": 89, "AwayMoneyLine": -101, "DrawMoneyLine": null, "HomePointSpread": 1.2, "AwayPointSpread": -1.7, "HomePointSpreadPayout": 69, "AwayPointSpreadPayout": -80, "OverUnder": 37.1, "OverPayout": -73, "UnderPayout": -73, "SportsbookId": 9, "OddType": "pregame", "SportsbookUrl": null}, {"GameOddId": 649488, "Sportsbook": "Scrambled", "ScoreId": 17353, "Created": "2020-10-18T16:24:47", "Updated": "2020-10-18T16:24:47", "HomeMoneyLine": 89, "AwayMoneyLine": -101, "DrawMoneyLine": null, "HomePointSpread": 1.2, "AwayPointSpread": -1.7, "HomePointSpreadPayout": 69, "AwayPointSpreadPayout": -80, "OverUnder": 37.1, "OverPayout": -73, "UnderPayout": -73, "SportsbookId": 10, "OddType": "pregame", "SportsbookUrl": null}, {"GameOddId": 649491, "Sportsbook": "Scrambled", "ScoreId": 17353, "Created": "2020-10-18T16:24:50", "Updated": "2020-10-18T16:24:50", "HomeMoneyLine": 85, "AwayMoneyLine": -106, "DrawMoneyLine": null, "HomePointSpread": 1.2, "AwayPointSpread": -1.7, "HomePointSpreadPayout": 68, "AwayPointSpreadPayout": -82, "OverUnder": 37.1, "OverPayout": -75, "UnderPayout": -75, "SportsbookId": 12, "OddType": "pregame", "SportsbookUrl": null}, {"GameOddId": 649490, "Sportsbook": "Scrambled", "ScoreId": 17353, "Created": "2020-10-18T16:24:49", "Updated": "2020-10-18T16:24:49", "HomeMoneyLine": 85, "AwayMoneyLine": -106, "DrawMoneyLine": null, "HomePointSpread": 1.2, "AwayPointSpread": -1.7, "HomePointSpreadPayout": 68, "AwayPointSpreadPayout": -82, "OverUnder": 37.1, "OverPayout": -75, "UnderPayout": -75, "SportsbookId": 13, "OddType": "pregame", "SportsbookUrl": null}, {"GameOddId": 649492, "Sportsbook": "Scrambled", "ScoreId": 17353, "Created": "2020-10-18T16:24:51", "Updated": "2020-10-18T16:24:51", "HomeMoneyLine": 89, "AwayMoneyLine": -101, "DrawMoneyLine": null, "HomePointSpread": 1.2, "AwayPointSpread": -1.7, "HomePointSpreadPayout": 69, "AwayPointSpreadPayout": -80, "OverUnder": 37.1, "OverPayout": -73, "UnderPayout": -73, "SportsbookId": 14, "OddType": "pregame", "SportsbookUrl": null}, {"GameOddId": 649497, "Sportsbook": "Scrambled", "ScoreId": 17353, "Created": "2020-10-18T16:24:54", "Updated": "2020-10-18T16:24:54", "HomeMoneyLine": 87, "AwayMoneyLine": -103, "DrawMoneyLine": null, "HomePointSpread": 1.2, "AwayPointSpread": -1.7, "HomePointSpreadPayout": 68, "AwayPointSpreadPayout": -82, "OverUnder": 37.1, "OverPayout": -74, "UnderPayout": -74, "SportsbookId": 22, "OddType": "pregame", "SportsbookUrl": null}, {"GameOddId": 649493, "Sportsbook": "Scrambled", "ScoreId": 17353, "Created": "2020-10-18T16:24:52", "Updated": "2020-10-18T16:24:52", "HomeMoneyLine": 89, "AwayMoneyLine": -102, "DrawMoneyLine": null, "HomePointSpread": 1.4, "AwayPointSpread": -2.0, "HomePointSpreadPayout": -82, "AwayPointSpreadPayout": 68, "OverUnder": 37.5, "OverPayout": -72, "UnderPayout": -78, "SportsbookId": 23, "OddType": "pregame", "SportsbookUrl": null}, {"GameOddId": 649495, "Sportsbook": "Scrambled", "ScoreId": 17353, "Created": "2020-10-18T16:24:52", "Updated": "2020-10-18T16:24:52", "HomeMoneyLine": 85, "AwayMoneyLine": -106, "DrawMoneyLine": null, "HomePointSpread": 1.2, "AwayPointSpread": -1.7, "HomePointSpreadPayout": 68, "AwayPointSpreadPayout": -82, "OverUnder": 37.1, "OverPayout": -75, "UnderPayout": -75, "SportsbookId": 25, "OddType": "pregame", "SportsbookUrl": null}], "LiveOdds": [], "AlternateMarketPregameOdds": []}, {"ScoreId": 17354, "Season": 2020, "SeasonType": 1, "Week": 6, "Day": "2020-10-18T00:00:00", "DateTime": "2020-10-18T20:20:00", "Status": "Final", "AwayTeamId": 32, "HomeTeamId": 31, "AwayTeamName": "LAR", "HomeTeamName": "SF", "GlobalGameId": 17354, "GlobalAwayTeamId": 32, "GlobalHomeTeamId": 31, "HomeTeamScore": 16, "AwayTeamScore": 11, "TotalScore": 27, "HomeRotationNumber": 187, "AwayRotationNumber": 186, "PregameOdds": [{"GameOddId": 651106, "Sportsbook": "Scrambled", "ScoreId": 17354, "Created": "2020-10-18T18:21:46", "Updated": "2020-10-18T20:19:49", "HomeMoneyLine": 80, "AwayMoneyLine": -91, "DrawMoneyLine": null, "HomePointSpread": 1.2, "AwayPointSpread": -1.7, "HomePointSpreadPayout": -76, "AwayPointSpreadPayout": -74, "OverUnder": 35.1, "OverPayout": -75, "UnderPayout": -75, "SportsbookId": 7, "OddType": "pregame", "SportsbookUrl": null}, {"GameOddId": 652055, "Sportsbook": "Scrambled", "ScoreId": 17354, "Created": "2020-10-18T20:06:11", "Updated": "2020-10-18T20:19:50", "HomeMoneyLine": 75, "AwayMoneyLine": -89, "DrawMoneyLine": null, "HomePointSpread": 1.2, "AwayPointSpread": -1.7, "HomePointSpreadPayout": -78, "AwayPointSpreadPayout": -72, "OverUnder": 35.1, "OverPayout": -72, "UnderPayout": -78, "SportsbookId": 8, "OddType": "pregame", "SportsbookUrl": null}, {"GameOddId": 651089, "Sportsbook": "Scrambled", "ScoreId": 17354, "Created": "2020-10-18T18:21:03", "Updated": "2020-10-18T20:19:51", "HomeMoneyLine": 80, "AwayMoneyLine": -91, "DrawMoneyLine": null, "HomePointSpread": 1.2, "AwayPointSpread": -1.7, "HomePointSpreadPayout": -74, "AwayPointSpreadPayout": -72, "OverUnder": 35.1, "OverPayout": -73, "UnderPayout": -73, "SportsbookId": 9, "OddType": "pregame", "SportsbookUrl": null}, {"GameOddId": 651088, "Sportsbook": "Scrambled", "ScoreId": 17354, "Created": "2020-10-18T18:21:02", "Updated": "2020-10-18T20:19:50", "HomeMoneyLine": 80, "AwayMoneyLine": -91, "DrawMoneyLine": null, "HomePointSpread": 1.2, "AwayPointSpread": -1.7, "HomePointSpreadPayout": -74, "AwayPointSpreadPayout": -72, "OverUnder": 35.1, "OverPayout": -73, "UnderPayout": -73, "SportsbookId": 10, "OddType": "pregame", "SportsbookUrl": null}, {"GameOddId": 651091, "Sportsbook": "Scrambled", "ScoreId": 17354, "Created": "2020-10-18T18:21:05", "Updated": "2020-10-18T20:19:53", "HomeMoneyLine": 78, "AwayMoneyLine": -95, "DrawMoneyLine": null, "HomePointSpread": 1.2, "AwayPointSpread": -1.7, "HomePointSpreadPayout": -76, "AwayPointSpreadPayout": -74, "OverUnder": 35.1, "OverPayout": -75, "UnderPayout": -75, "SportsbookId": 12, "OddType": "pregame", "SportsbookUrl": null}, {"GameOddId": 651090, "Sportsbook": "Scrambled", "ScoreId": 17354, "Created": "2020-10-18T18:21:04", "Updated": "2020-10-18T20:19:52", "HomeMoneyLine": 78, "AwayMoneyLine": -95, "DrawMoneyLine": null, "HomePointSpread": 1.2, "AwayPointSpread": -1.7, "HomePointSpreadPayout": -76, "AwayPointSpreadPayout": -74, "OverUnder": 35.1, "OverPayout": -75, "UnderPayout": -75, "SportsbookId": 13, "OddType": "pregame", "SportsbookUrl": null}, {"GameOddId": 651092, "Sportsbook": "Scrambled", "ScoreId": 17354, "Created": "2020-10-18T18:21:07", "Updated": "2020-10-18T20:19:54", "HomeMoneyLine": 80, "AwayMoneyLine": -91, "DrawMoneyLine": null, "HomePointSpread": 1.2, "AwayPointSpread": -1.7, "HomePointSpreadPayout": -74, "AwayPointSpreadPayout": -72, "OverUnder": 35.1, "OverPayout": -73, "UnderPayout": -73, "SportsbookId": 14, "OddType": "pregame", "SportsbookUrl": null}, {"GameOddId": 652060, "Sportsbook": "Scrambled", "ScoreId": 17354, "Created": "2020-10-18T20:06:20", "Updated": "2020-10-18T20:19:57", "HomeMoneyLine": 78, "AwayMoneyLine": -92, "DrawMoneyLine": null, "HomePointSpread": 1.2, "AwayPointSpread": -1.7, "HomePointSpreadPayout": -76, "AwayPointSpreadPayout": -74, "OverUnder": 35.1, "OverPayout": -74, "UnderPayout": -74, "SportsbookId": 22, "OddType": "pregame", "SportsbookUrl": null}, {"GameOddId": 652105, "Sportsbook": "Scrambled", "ScoreId": 17354, "Created": "2020-10-18T20:19:33", "Updated": "2020-10-18T20:19:55", "HomeMoneyLine": 75, "AwayMoneyLine": -89, "DrawMoneyLine": null, "HomePointSpread": 1.2, "AwayPointSpread": -1.7, "HomePointSpreadPayout": -78, "AwayPointSpreadPayout": -72, "OverUnder": 34.7, "OverPayout": -82, "UnderPayout": 68, "SportsbookId": 23, "OddType": "pregame", "SportsbookUrl": null}, {"GameOddId": 651096, "Sportsbook": "Scrambled", "ScoreId": 17354, "Created": "2020-10-18T18:21:10", "Updated": "2020-10-18T20:19:56", "HomeMoneyLine": 78, "AwayMoneyLine": -95, "DrawMoneyLine": null, "HomePointSpread": 1.2, "AwayPointSpread": -1.7, "HomePointSpreadPayout": -76, "AwayPointSpreadPayout": -74, "OverUnder": 35.1, "OverPayout": -75, "UnderPayout": -75, "SportsbookId": 25, "OddType": "pregame", "SportsbookUrl": null}], "LiveOdds": [], "AlternateMarketPregameOdds": []}, {"ScoreId": 17342, "Season": 2020, "SeasonType": 1, "Week": 6, "Day": "2020-10-19T00:00:00", "DateTime": "2020-10-19T17:00:00", "Status": "Final", "AwayTeamId": 16, "HomeTeamId": 4, "AwayTeamName": "KC", "HomeTeamName": "BUF", "GlobalGameId": 17342, "GlobalAwayTeamId": 16, "GlobalHomeTeamId": 4, "HomeTeamScore": 12, "AwayTeamScore": 18, "TotalScore": 29, "HomeRotationNumber": 189, "AwayRotationNumber": 189, "PregameOdds": [{"GameOddId": 654404, "Sportsbook": "Scrambled", "ScoreId": 17342, "Created": "2020-10-19T16:53:49", "Updated": "2020-10-19T16:59:41", "HomeMoneyLine": 143, "AwayMoneyLine": -167, "DrawMoneyLine": null, "HomePointSpread": 2.6, "AwayPointSpread": -3.7, "HomePointSpreadPayout": -75, "AwayPointSpreadPayout": -75, "OverUnder": 37.1, "OverPayout": -75, "UnderPayout": -75, "SportsbookId": 7, "OddType": "pregame", "SportsbookUrl": null}, {"GameOddId": 654337, "Sportsbook": "Scrambled", "ScoreId": 17342, "Created": "2020-10-19T16:05:52", "Updated": "2020-10-19T16:59:42", "HomeMoneyLine": 136, "AwayMoneyLine": -167, "DrawMoneyLine": null, "HomePointSpread": 2.6, "AwayPointSpread": -3.7, "HomePointSpreadPayout": -75, "AwayPointSpreadPayout": -75, "OverUnder": 37.1, "OverPayout": -75, "UnderPayout": -75, "SportsbookId": 8, "OddType": "pregame", "SportsbookUrl": null}, {"GameOddId": 654394, "Sportsbook": "Scrambled", "ScoreId": 17342, "Created": "2020-10-19T16:52:31", "Updated": "2020-10-19T16:59:21", "HomeMoneyLine": 143, "AwayMoneyLine": -167, "DrawMoneyLine": null, "HomePointSpread": 2.6, "AwayPointSpread": -3.7, "HomePointSpreadPayout": -73, "AwayPointSpreadPayout": -73, "OverUnder": 37.1, "OverPayout": -73, "UnderPayout": -73, "SportsbookId": 9, "OddType": "pregame", "SportsbookUrl": null}, {"GameOddId": 654393, "Sportsbook": "Scrambled", "ScoreId": 17342, "Created": "2020-10-19T16:52:30", "Updated": "2020-10-19T16:59:21", "HomeMoneyLine": 143, "AwayMoneyLine": -167, "DrawMoneyLine": null, "HomePointSpread": 2.6, "AwayPointSpread": -3.7, "HomePointSpreadPayout": -73, "AwayPointSpreadPayout": -73, "OverUnder": 37.1, "OverPayout": -73, "UnderPayout": -73, "SportsbookId": 10, "OddType": "pregame", "SportsbookUrl": null}, {"GameOddId": 654396, "Sportsbook": "Scrambled", "ScoreId": 17342, "Created": "2020-10-19T16:52:35", "Updated": "2020-10-19T16:59:23", "HomeMoneyLine": 136, "AwayMoneyLine": -170, "DrawMoneyLine": null, "HomePointSpread": 2.6, "AwayPointSpread": -3.7, "HomePointSpreadPayout": -75, "AwayPointSpreadPayout": -75, "OverUnder": 37.1, "OverPayout": -75, "UnderPayout": -75, "SportsbookId": 12, "OddType": "pregame", "SportsbookUrl": null}, {"GameOddId": 654395, "Sportsbook": "Scrambled", "ScoreId": 17342, "Created": "2020-10-19T16:52:33", "Updated": "2020-10-19T16:59:22", "HomeMoneyLine": 136, "AwayMoneyLine": -170, "DrawMoneyLine": null, "HomePointSpread": 2.6, "AwayPointSpread": -3.7, "HomePointSpreadPayout": -75, "AwayPointSpreadPayout": -75, "OverUnder": 37.1, "OverPayout": -75, "UnderPayout": -75, "SportsbookId": 13, "OddType": "pregame", "SportsbookUrl": null}, {"GameOddId": 654397, "Sportsbook": "Scrambled", "ScoreId": 17342, "Created": "2020-10-19T16:52:36", "Updated": "2020-10-19T16:59:24", "HomeMoneyLine": 143, "AwayMoneyLine": -167, "DrawMoneyLine": null, "HomePointSpread": 2.6, "AwayPointSpread": -3.7, "HomePointSpreadPayout": -73, "AwayPointSpreadPayout": -73, "OverUnder": 37.1, "OverPayout": -73, "UnderPayout": -73, "SportsbookId": 14, "OddType": "pregame", "SportsbookUrl": null}, {"GameOddId": 654408, "Sportsbook": "Scrambled", "ScoreId": 17342, "Created": "2020-10-19T16:59:51", "Updated": "2020-10-19T16:59:51", "HomeMoneyLine": 139, "AwayMoneyLine": -168, "DrawMoneyLine": null, "HomePointSpread": 2.6, "AwayPointSpread": -3.7, "HomePointSpreadPayout": -75, "AwayPointSpreadPayout": -75, "OverUnder": 37.1, "OverPayout": -74, "UnderPayout": -74, "SportsbookId": 22, "OddType": "pregame", "SportsbookUrl": null}, {"GameOddId": 654407, "Sportsbook": "Scrambled", "ScoreId": 17342, "Created": "2020-10-19T16:59:49", "Updated": "2020-10-19T16:59:49", "HomeMoneyLine": 133, "AwayMoneyLine": -167, "DrawMoneyLine": null, "HomePointSpread": 2.6, "AwayPointSpread": -3.7, "HomePointSpreadPayout": -75, "AwayPointSpreadPayout": -75, "OverUnder": 37.5, "OverPayout": -75, "UnderPayout": -75, "SportsbookId": 23, "OddType": "pregame", "SportsbookUrl": null}, {"GameOddId": 654398, "Sportsbook": "Scrambled", "ScoreId": 17342, "Created": "2020-10-19T16:52:40", "Updated": "2020-10-19T16:59:26", "HomeMoneyLine": 136, "AwayMoneyLine": -170, "DrawMoneyLine": null, "HomePointSpread": 2.6, "AwayPointSpread": -3.7, "HomePointSpreadPayout": -75, "AwayPointSpreadPayout": -75, "OverUnder": 37.1, "OverPayout": -75, "UnderPayout": -75, "SportsbookId": 25, "OddType": "pregame", "SportsbookUrl": null}], "LiveOdds": [], "AlternateMarketPregameOdds": []}, {"ScoreId": 17355, "Season": 2020, "SeasonType": 1, "Week": 6, "Day": "2020-10-19T00:00:00", "DateTime": "2020-10-19T20:15:00", "Status": "Final", "AwayTeamId": 1, "HomeTeamId": 9, "AwayTeamName": "ARI", "HomeTeamName": "DAL", "GlobalGameId": 17355, "GlobalAwayTeamId": 1, "GlobalHomeTeamId": 9, "HomeTeamScore": 5, "AwayTeamScore": 26, "TotalScore": 33, "HomeRotationNumber": 188, "AwayRotationNumber": 187, "PregameOdds": [{"GameOddId": 655719, "Sportsbook": "Scrambled", "ScoreId": 17355, "Created": "2020-10-19T20:06:48", "Updated": "2020-10-19T20:14:46", "HomeMoneyLine": -78, "AwayMoneyLine": 68, "DrawMoneyLine": null, "HomePointSpread": -0.7, "AwayPointSpread": 0.5, "HomePointSpreadPayout": -75, "AwayPointSpreadPayout": -75, "OverUnder": 37.8, "OverPayout": -75, "UnderPayout": -75, "SportsbookId": 7, "OddType": "pregame", "SportsbookUrl": null}, {"GameOddId": 655724, "Sportsbook": "Scrambled", "ScoreId": 17355, "Created": "2020-10-19T20:09:35", "Updated": "2020-10-19T20:14:47", "HomeMoneyLine": -80, "AwayMoneyLine": 68, "DrawMoneyLine": null, "HomePointSpread": -0.7, "AwayPointSpread": 0.5, "HomePointSpreadPayout": -75, "AwayPointSpreadPayout": -75, "OverUnder": 37.8, "OverPayout": -78, "UnderPayout": -72, "SportsbookId": 8, "OddType": "pregame", "SportsbookUrl": null}, {"GameOddId": 655713, "Sportsbook": "Scrambled", "ScoreId": 17355, "Created": "2020-10-19T20:06:02", "Updated": "2020-10-19T20:14:49", "HomeMoneyLine": -78, "AwayMoneyLine": 68, "DrawMoneyLine": null, "HomePointSpread": -0.7, "AwayPointSpread": 0.5, "HomePointSpreadPayout": -73, "AwayPointSpreadPayout": -73, "OverUnder": 37.8, "OverPayout": -73, "UnderPayout": -73, "SportsbookId": 9, "OddType": "pregame", "SportsbookUrl": null}, {"GameOddId": 655712, "Sportsbook": "Scrambled", "ScoreId": 17355, "Created": "2020-10-19T20:06:00", "Updated": "2020-10-19T20:14:49", "HomeMoneyLine": -78, "AwayMoneyLine": 68, "DrawMoneyLine": null, "HomePointSpread": -0.7, "AwayPointSpread": 0.5, "HomePointSpreadPayout": -73, "AwayPointSpreadPayout": -73, "OverUnder": 37.8, "OverPayout": -73, "UnderPayout": -73, "SportsbookId": 10, "OddType": "pregame", "SportsbookUrl": null}, {"GameOddId": 655715, "Sportsbook": "Scrambled", "ScoreId": 17355, "Created": "2020-10-19T20:06:05", "Updated": "2020-10-19T20:14:51", "HomeMoneyLine": -80, "AwayMoneyLine": -71, "DrawMoneyLine": null, "HomePointSpread": -0.7, "AwayPointSpread": 0.5, "HomePointSpreadPayout": -75, "AwayPointSpreadPayout": -75, "OverUnder": 37.8, "OverPayout": -75, "UnderPayout": -75, "SportsbookId": 12, "OddType": "pregame", "SportsbookUrl": null}, {"GameOddId": 655714, "Sportsbook": "Scrambled", "ScoreId": 17355, "Created": "2020-10-19T20:06:03", "Updated": "2020-10-19T20:14:50", "HomeMoneyLine": -80, "AwayMoneyLine": -71, "DrawMoneyLine": null, "HomePointSpread": -0.7, "AwayPointSpread": 0.5, "HomePointSpreadPayout": -75, "AwayPointSpreadPayout": -75, "OverUnder": 37.8, "OverPayout": -75, "UnderPayout": -75, "SportsbookId": 13, "OddType": "pregame", "SportsbookUrl": null}, {"GameOddId": 655716, "Sportsbook": "Scrambled", "ScoreId": 17355, "Created": "2020-10-19T20:06:06", "Updated": "2020-10-19T20:14:52", "HomeMoneyLine": -78, "AwayMoneyLine": 68, "DrawMoneyLine": null, "HomePointSpread": -0.7, "AwayPointSpread": 0.5, "HomePointSpreadPayout": -73, "AwayPointSpreadPayout": -73, "OverUnder": 37.8, "OverPayout": -73, "UnderPayout": -73, "SportsbookId": 14, "OddType": "pregame", "SportsbookUrl": null}, {"GameOddId": 655736, "Sportsbook": "Scrambled", "ScoreId": 17355, "Created": "2020-10-19T20:14:57", "Updated": "2020-10-19T20:14:57", "HomeMoneyLine": -79, "AwayMoneyLine": -69, "DrawMoneyLine": null, "HomePointSpread": -0.7, "AwayPointSpread": 0.5, "HomePointSpreadPayout": -75, "AwayPointSpreadPayout": -75, "OverUnder": 37.8, "OverPayout": -74, "UnderPayout": -74, "SportsbookId": 22, "OddType": "pregame", "SportsbookUrl": null}, {"GameOddId": 655735, "Sportsbook": "Scrambled", "ScoreId": 17355, "Created": "2020-10-19T20:14:54", "Updated": "2020-10-19T20:14:54", "HomeMoneyLine": -78, "AwayMoneyLine": -72, "DrawMoneyLine": null, "HomePointSpread": -0.7, "AwayPointSpread": 0.5, "HomePointSpreadPayout": -75, "AwayPointSpreadPayout": -75, "OverUnder": 38.1, "OverPayout": -75, "UnderPayout": -75, "SportsbookId": 23, "OddType": "pregame", "SportsbookUrl": null}, {"GameOddId": 655717, "Sportsbook": "Scrambled", "ScoreId": 17355, "Created": "2020-10-19T20:06:08", "Updated": "2020-10-19T20:14:56", "HomeMoneyLine": -80, "AwayMoneyLine": -71, "DrawMoneyLine": null, "HomePointSpread": -0.7, "AwayPointSpread": 0.5, "HomePointSpreadPayout": -75, "AwayPointSpreadPayout": -75, "OverUnder": 37.8, "OverPayout": -75, "UnderPayout": -75, "SportsbookId": 25, "OddType": "pregame", "SportsbookUrl": null}], "LiveOdds": [], "AlternateMarketPregameOdds": []}]